{"v":"5.12.1","fr":30,"ip":0,"op":80,"w":1600,"h":1600,"nm":"Graduate Stacks","ddd":0,"assets":[],"layers":[{"ddd":0,"ind":1,"ty":4,"nm":"Hat","sr":1,"ks":{"o":{"a":0,"k":100},"r":{"a":1,"k":[{"i":{"x":[0.667],"y":[1]},"o":{"x":[0.333],"y":[0]},"t":-27,"s":[0]},{"i":{"x":[0.667],"y":[1]},"o":{"x":[0.333],"y":[0]},"t":13,"s":[11]},{"i":{"x":[0.667],"y":[1]},"o":{"x":[0.333],"y":[0]},"t":53,"s":[0]},{"i":{"x":[0.667],"y":[1]},"o":{"x":[0.333],"y":[0]},"t":93,"s":[11]},{"t":133,"s":[0]}]},"p":{"a":1,"k":[{"i":{"x":0.667,"y":1},"o":{"x":0.333,"y":0},"t":-37,"s":[824,524,0],"to":[0,0,0],"ti":[0,0,0]},{"i":{"x":0.667,"y":1},"o":{"x":0.333,"y":0},"t":3,"s":[824,482.4,0],"to":[0,0,0],"ti":[0,0,0]},{"i":{"x":0.667,"y":1},"o":{"x":0.333,"y":0},"t":43,"s":[824,524,0],"to":[0,0,0],"ti":[0,0,0]},{"i":{"x":0.667,"y":1},"o":{"x":0.333,"y":0},"t":83,"s":[824,482.4,0],"to":[0,0,0],"ti":[0,0,0]},{"t":123,"s":[824,524,0]}]},"a":{"a":0,"k":[22.054,-236.03,0]},"s":{"a":0,"k":[100,100,100]}},"ao":0,"shapes":[{"ty":"gr","it":[{"ty":"gr","it":[{"ind":0,"ty":"sh","ks":{"a":1,"k":[{"i":{"x":0.667,"y":1},"o":{"x":0.333,"y":0},"t":-20,"s":[{"i":[[0,0],[-1.952,-5.945],[0.268,-7.57],[-42.987,-3.432]],"o":[[26.711,32.157],[2.363,7.197],[-1.517,42.885],[0,0]],"v":[[33.242,-304.198],[99.159,-223.276],[101.174,-200.765],[140.253,-105.892]],"c":false}]},{"i":{"x":0.667,"y":1},"o":{"x":0.333,"y":0},"t":20,"s":[{"i":[[0,0],[-1.952,-5.945],[-2.038,-7.296],[-29.679,13.802]],"o":[[26.711,32.157],[2.363,7.197],[11.547,41.329],[0,0]],"v":[[33.242,-304.198],[99.159,-223.276],[106.604,-202.436],[179.426,-138.622]],"c":false}]},{"i":{"x":0.667,"y":1},"o":{"x":0.333,"y":0},"t":60,"s":[{"i":[[0,0],[-1.952,-5.945],[0.268,-7.57],[-42.987,-3.432]],"o":[[26.711,32.157],[2.363,7.197],[-1.517,42.885],[0,0]],"v":[[33.242,-304.198],[99.159,-223.276],[101.174,-200.765],[140.253,-105.892]],"c":false}]},{"i":{"x":0.667,"y":1},"o":{"x":0.333,"y":0},"t":100,"s":[{"i":[[0,0],[-1.952,-5.945],[-2.038,-7.296],[-29.679,13.802]],"o":[[26.711,32.157],[2.363,7.197],[11.547,41.329],[0,0]],"v":[[33.242,-304.198],[99.159,-223.276],[106.604,-202.436],[179.426,-138.622]],"c":false}]},{"t":140,"s":[{"i":[[0,0],[-1.952,-5.945],[0.268,-7.57],[-42.987,-3.432]],"o":[[26.711,32.157],[2.363,7.197],[-1.517,42.885],[0,0]],"v":[[33.242,-304.198],[99.159,-223.276],[101.174,-200.765],[140.253,-105.892]],"c":false}]}]},"nm":"Path 1","hd":false},{"ty":"st","c":{"a":0,"k":[0.007843137719,0.007843137719,0.007843137719,1]},"o":{"a":0,"k":100},"w":{"a":0,"k":2},"lc":2,"lj":2,"bm":0,"nm":"Stroke 1","hd":false},{"ty":"tr","p":{"a":0,"k":[0,0]},"a":{"a":0,"k":[0,0]},"s":{"a":0,"k":[100,100]},"r":{"a":0,"k":0},"o":{"a":0,"k":100},"sk":{"a":0,"k":0},"sa":{"a":0,"k":0},"nm":"Transform"}],"nm":"Group 1","bm":0,"hd":false},{"ty":"gr","it":[{"ind":0,"ty":"sh","ks":{"a":1,"k":[{"i":{"x":0.667,"y":1},"o":{"x":0.333,"y":0},"t":-20,"s":[{"i":[[2.189,-0.237],[0.311,-0.43],[0.14,-1.131],[-2.687,-3.199],[-0.907,-0.19],[-0.569,2.598]],"o":[[-0.528,0.057],[-0.668,0.924],[-0.21,1.697],[0.596,0.709],[1.59,0.333],[0.409,-1.871]],"v":[[141.923,-107.559],[139.615,-107.622],[138.616,-104.458],[146.301,-88.903],[148.486,-87.275],[160.433,-107.18]],"c":true}]},{"i":{"x":0.667,"y":1},"o":{"x":0.333,"y":0},"t":20,"s":[{"i":[[0.576,-2.126],[-0.032,-0.53],[-1.003,-0.542],[-3.957,1.34],[-0.506,0.776],[2.214,1.474]],"o":[[-0.139,0.512],[0.068,1.138],[1.505,0.813],[0.877,-0.297],[0.888,-1.36],[-1.594,-1.062]],"v":[[178.083,-141.122],[177.837,-139.557],[179.77,-136.914],[197.055,-138.417],[199.366,-139.86],[185.167,-158.227]],"c":true}]},{"i":{"x":0.667,"y":1},"o":{"x":0.333,"y":0},"t":60,"s":[{"i":[[2.189,-0.237],[0.311,-0.43],[0.14,-1.131],[-2.687,-3.199],[-0.907,-0.19],[-0.569,2.598]],"o":[[-0.528,0.057],[-0.668,0.924],[-0.21,1.697],[0.596,0.709],[1.59,0.333],[0.409,-1.871]],"v":[[141.923,-107.559],[139.615,-107.622],[138.616,-104.458],[146.301,-88.903],[148.486,-87.275],[160.433,-107.18]],"c":true}]},{"i":{"x":0.667,"y":1},"o":{"x":0.333,"y":0},"t":100,"s":[{"i":[[0.576,-2.126],[-0.032,-0.53],[-1.003,-0.542],[-3.957,1.34],[-0.506,0.776],[2.214,1.474]],"o":[[-0.139,0.512],[0.068,1.138],[1.505,0.813],[0.877,-0.297],[0.888,-1.36],[-1.594,-1.062]],"v":[[178.083,-141.122],[177.837,-139.557],[179.77,-136.914],[197.055,-138.417],[199.366,-139.86],[185.167,-158.227]],"c":true}]},{"t":140,"s":[{"i":[[2.189,-0.237],[0.311,-0.43],[0.14,-1.131],[-2.687,-3.199],[-0.907,-0.19],[-0.569,2.598]],"o":[[-0.528,0.057],[-0.668,0.924],[-0.21,1.697],[0.596,0.709],[1.59,0.333],[0.409,-1.871]],"v":[[141.923,-107.559],[139.615,-107.622],[138.616,-104.458],[146.301,-88.903],[148.486,-87.275],[160.433,-107.18]],"c":true}]}]},"nm":"Path 1","hd":false},{"ty":"fl","c":{"a":0,"k":[0.007843137719,0.007843137719,0.007843137719,1]},"o":{"a":0,"k":100},"r":1,"bm":0,"nm":"Fill 1","hd":false},{"ty":"tr","p":{"a":0,"k":[0,0]},"a":{"a":0,"k":[0,0]},"s":{"a":0,"k":[100,100]},"r":{"a":0,"k":0},"o":{"a":0,"k":100},"sk":{"a":0,"k":0},"sa":{"a":0,"k":0},"nm":"Transform"}],"nm":"Group 2","bm":0,"hd":false},{"ty":"gr","it":[{"ind":0,"ty":"sh","ks":{"a":0,"k":{"i":[[-7.381,-2.689],[1.134,-3.113],[7.381,2.689],[-1.134,3.113]],"o":[[7.381,2.689],[-1.134,3.113],[-7.381,-2.689],[1.134,-3.113]],"v":[[34.869,-309.186],[46.18,-298.68],[30.762,-297.911],[19.451,-308.417]],"c":true}},"nm":"Path 1","hd":false},{"ty":"fl","c":{"a":0,"k":[0.007843137719,0.007843137719,0.007843137719,1]},"o":{"a":0,"k":100},"r":1,"bm":0,"nm":"Fill 1","hd":false},{"ty":"tr","p":{"a":0,"k":[0,0]},"a":{"a":0,"k":[0,0]},"s":{"a":0,"k":[100,100]},"r":{"a":0,"k":0},"o":{"a":0,"k":100},"sk":{"a":0,"k":0},"sa":{"a":0,"k":0},"nm":"Transform"}],"nm":"Group 3","bm":0,"hd":false},{"ty":"tr","p":{"a":0,"k":[0,0]},"a":{"a":0,"k":[0,0]},"s":{"a":0,"k":[100,100]},"r":{"a":0,"k":0},"o":{"a":0,"k":100},"sk":{"a":0,"k":0},"sa":{"a":0,"k":0},"nm":"Transform"}],"nm":"Group 1","bm":0,"hd":false},{"ty":"gr","it":[{"ind":0,"ty":"sh","ks":{"a":0,"k":{"i":[[0,0],[-10.348,-2.726],[-6.643,-0.152],[-36.577,-2.485]],"o":[[42.136,37.753],[6.425,1.693],[35.656,0.815],[0,0]],"v":[[-103.638,-316.234],[1.939,-230.42],[21.722,-228.414],[130.857,-222.041]],"c":false}},"nm":"Path 1","hd":false},{"ty":"st","c":{"a":0,"k":[1,1,1,1]},"o":{"a":0,"k":100},"w":{"a":0,"k":2},"lc":2,"lj":2,"bm":0,"nm":"Stroke 1","hd":false},{"ty":"tr","p":{"a":0,"k":[0,0]},"a":{"a":0,"k":[0,0]},"s":{"a":0,"k":[100,100]},"r":{"a":0,"k":0},"o":{"a":0,"k":100},"sk":{"a":0,"k":0},"sa":{"a":0,"k":0},"nm":"Transform"}],"nm":"Group 2","bm":0,"hd":false},{"ty":"gr","it":[{"ind":0,"ty":"sh","ks":{"a":0,"k":{"i":[[-17.306,-4.559],[-6.643,-0.152],[-56.573,-1.293],[-1.074,3.683],[36.526,33.036],[3.897,1.6],[4.471,0.214],[6.228,-1.151],[-2.704,-4.211]],"o":[[6.425,1.693],[56.573,1.293],[3.181,0.073],[2.916,-9.055],[-3.124,-2.826],[-4.141,-1.7],[-45.081,-2.154],[-7.184,1.328],[5.224,8.137]],"v":[[1.939,-230.42],[21.722,-228.414],[194.576,-218.85],[205.319,-221.659],[64.54,-357.489],[54.251,-364.712],[41.067,-366.86],[-157.354,-377.854],[-157.449,-366.847]],"c":true}},"nm":"Path 1","hd":false},{"ty":"fl","c":{"a":0,"k":[0.063,0,0.361]},"o":{"a":0,"k":100},"r":1,"bm":0,"nm":"Fill 1","hd":false},{"ty":"tr","p":{"a":0,"k":[0,0]},"a":{"a":0,"k":[0,0]},"s":{"a":0,"k":[100,100]},"r":{"a":0,"k":0},"o":{"a":0,"k":100},"sk":{"a":0,"k":0},"sa":{"a":0,"k":0},"nm":"Transform"}],"nm":"Group 3","bm":0,"hd":false},{"ty":"gr","it":[{"ind":0,"ty":"sh","ks":{"a":0,"k":{"i":[[3.056,-12.515],[-1.136,-3.288],[-2.329,-2.195],[-72.538,-14.396],[-7.958,2.76],[-5.104,12.833],[-1.912,17.555],[1.461,3.802],[2.846,2.55],[8.549,4.677],[46.788,18.346],[12.104,2.67],[6.093,-1.768],[1.758,-3.648]],"o":[[-0.825,3.379],[1.045,3.025],[53.814,50.726],[8.262,1.64],[13.048,-4.524],[6.526,-16.409],[0.441,-4.049],[-1.371,-3.567],[-7.258,-6.502],[-44.089,-24.121],[-11.539,-4.525],[-6.009,-1.325],[-4.25,1.233],[-6.454,13.389]],"v":[[-138.01,-247.226],[-138.287,-236.942],[-132.547,-229.369],[66.163,-137.468],[91.119,-137.119],[115.991,-168.57],[130.619,-219.313],[129.788,-231.385],[122.864,-240.383],[98.555,-256.498],[-39.257,-317.378],[-74.497,-329.115],[-94.889,-330.735],[-101.93,-322.153]],"c":true}},"nm":"Path 1","hd":false},{"ty":"fl","c":{"a":0,"k":[0.063,0,0.361]},"o":{"a":0,"k":100},"r":1,"bm":0,"nm":"Fill 1","hd":false},{"ty":"tr","p":{"a":0,"k":[0,0]},"a":{"a":0,"k":[0,0]},"s":{"a":0,"k":[100,100]},"r":{"a":0,"k":0},"o":{"a":0,"k":100},"sk":{"a":0,"k":0},"sa":{"a":0,"k":0},"nm":"Transform"}],"nm":"Group 4","bm":0,"hd":false}],"ip":-37,"op":174,"st":-37,"ct":1,"bm":0},{"ddd":0,"ind":2,"ty":4,"nm":"P 1","sr":1,"ks":{"o":{"a":0,"k":100},"r":{"a":1,"k":[{"i":{"x":[0.667],"y":[1]},"o":{"x":[0.333],"y":[0]},"t":-19,"s":[0]},{"i":{"x":[0.667],"y":[1]},"o":{"x":[0.333],"y":[0]},"t":21,"s":[20]},{"i":{"x":[0.667],"y":[1]},"o":{"x":[0.333],"y":[0]},"t":61,"s":[0]},{"i":{"x":[0.667],"y":[1]},"o":{"x":[0.333],"y":[0]},"t":101,"s":[20]},{"t":141,"s":[0]}]},"p":{"a":1,"k":[{"i":{"x":0.667,"y":1},"o":{"x":0.333,"y":0},"t":-29,"s":[1110.554,669.97,0],"to":[0,0,0],"ti":[0,0,0]},{"i":{"x":0.667,"y":1},"o":{"x":0.333,"y":0},"t":11,"s":[1110.554,741.97,0],"to":[0,0,0],"ti":[0,0,0]},{"i":{"x":0.667,"y":1},"o":{"x":0.333,"y":0},"t":51,"s":[1110.554,669.97,0],"to":[0,0,0],"ti":[0,0,0]},{"i":{"x":0.667,"y":1},"o":{"x":0.333,"y":0},"t":91,"s":[1110.554,741.97,0],"to":[0,0,0],"ti":[0,0,0]},{"t":131,"s":[1110.554,669.97,0]}]},"a":{"a":0,"k":[250.385,-114.205,0]},"s":{"a":0,"k":[100,100,100]}},"ao":0,"shapes":[{"ty":"gr","it":[{"ind":0,"ty":"sh","ks":{"a":0,"k":{"i":[[0,0],[0,0]],"o":[[0,0],[0,0]],"v":[[268.284,-158.094],[289.891,-139.133]],"c":false}},"nm":"Path 1","hd":false},{"ty":"st","c":{"a":0,"k":[1,1,1,1]},"o":{"a":0,"k":100},"w":{"a":0,"k":2},"lc":2,"lj":2,"bm":0,"nm":"Stroke 1","hd":false},{"ty":"fl","c":{"a":0,"k":[0.612,0.733,0.984]},"o":{"a":0,"k":100},"r":1,"bm":0,"nm":"Fill 1","hd":false},{"ty":"tr","p":{"a":0,"k":[0,0]},"a":{"a":0,"k":[0,0]},"s":{"a":0,"k":[100,100]},"r":{"a":0,"k":0},"o":{"a":0,"k":100},"sk":{"a":0,"k":0},"sa":{"a":0,"k":0},"nm":"Transform"}],"nm":"Group 1","bm":0,"hd":false},{"ty":"gr","it":[{"ind":0,"ty":"sh","ks":{"a":0,"k":{"i":[[0,0],[0.327,-2.79],[6.703,-7.594]],"o":[[0,0],[-0.327,2.79],[0,0]],"v":[[340.036,-196.038],[346.317,-188.318],[316.196,-154.414]],"c":false}},"nm":"Path 1","hd":false},{"ty":"st","c":{"a":0,"k":[0.007843137719,0.007843137719,0.007843137719,1]},"o":{"a":0,"k":100},"w":{"a":0,"k":2},"lc":2,"lj":2,"bm":0,"nm":"Stroke 1","hd":false},{"ty":"tr","p":{"a":0,"k":[0,0]},"a":{"a":0,"k":[0,0]},"s":{"a":0,"k":[100,100]},"r":{"a":0,"k":0},"o":{"a":0,"k":100},"sk":{"a":0,"k":0},"sa":{"a":0,"k":0},"nm":"Transform"}],"nm":"Group 2","bm":0,"hd":false},{"ty":"gr","it":[{"ind":0,"ty":"sh","ks":{"a":0,"k":{"i":[[-3.599,1.784],[3.814,1.908],[-1.221,-0.72]],"o":[[-0.747,-2.135],[-1.964,5.554],[0.885,0.522]],"v":[[153.531,3.705],[146.123,-4.173],[143.719,7.812]],"c":true}},"nm":"Path 1","hd":false},{"ty":"fl","c":{"a":0,"k":[0.007843137719,0.007843137719,0.007843137719,1]},"o":{"a":0,"k":100},"r":1,"bm":0,"nm":"Fill 1","hd":false},{"ty":"tr","p":{"a":0,"k":[0,0]},"a":{"a":0,"k":[0,0]},"s":{"a":0,"k":[100,100]},"r":{"a":0,"k":0},"o":{"a":0,"k":100},"sk":{"a":0,"k":0},"sa":{"a":0,"k":0},"nm":"Transform"}],"nm":"Group 3","bm":0,"hd":false},{"ty":"gr","it":[{"ind":0,"ty":"sh","ks":{"a":0,"k":{"i":[[2.892,1.704],[-4.536,5.66],[-7.345,2.304],[0.407,-5.365],[21.536,-23.576],[5.944,-6.635]],"o":[[-3.158,-1.861],[4.536,-5.66],[7.345,-2.304],[-0.407,5.365],[-21.536,23.576],[-5.894,6.578]],"v":[[145.075,5.934],[156.093,-26.63],[333.083,-231.405],[352.9,-215.017],[224.783,-63.757],[175.24,-10.069]],"c":true}},"nm":"Path 1","hd":false},{"ty":"fl","c":{"a":0,"k":[0.612,0.733,0.984]},"o":{"a":0,"k":100},"r":1,"bm":0,"nm":"Fill 1","hd":false},{"ty":"tr","p":{"a":0,"k":[0,0]},"a":{"a":0,"k":[0,0]},"s":{"a":0,"k":[100,100]},"r":{"a":0,"k":0},"o":{"a":0,"k":100},"sk":{"a":0,"k":0},"sa":{"a":0,"k":0},"nm":"Transform"}],"nm":"Group 4","bm":0,"hd":false},{"ty":"gr","it":[{"ind":0,"ty":"sh","ks":{"a":0,"k":{"i":[[0,0],[-4.647,0.141],[1.37,-1.976],[0,0]],"o":[[0,0],[4.647,-0.141],[-3.788,5.466],[0,0]],"v":[[334.473,-223.625],[348.435,-236.284],[357.256,-226.768],[343.483,-213.117]],"c":true}},"nm":"Path 1","hd":false},{"ty":"fl","c":{"a":0,"k":[1,1,1,1]},"o":{"a":0,"k":100},"r":1,"bm":0,"nm":"Fill 1","hd":false},{"ty":"tr","p":{"a":0,"k":[0,0]},"a":{"a":0,"k":[0,0]},"s":{"a":0,"k":[100,100]},"r":{"a":0,"k":0},"o":{"a":0,"k":100},"sk":{"a":0,"k":0},"sa":{"a":0,"k":0},"nm":"Transform"}],"nm":"Group 5","bm":0,"hd":false}],"ip":-29,"op":121,"st":-29,"ct":1,"bm":0},{"ddd":0,"ind":3,"ty":4,"nm":"P 2","sr":1,"ks":{"o":{"a":0,"k":100},"r":{"a":1,"k":[{"i":{"x":[0.667],"y":[1]},"o":{"x":[0.333],"y":[0]},"t":-31,"s":[0]},{"i":{"x":[0.667],"y":[1]},"o":{"x":[0.333],"y":[0]},"t":9,"s":[20]},{"i":{"x":[0.667],"y":[1]},"o":{"x":[0.333],"y":[0]},"t":49,"s":[0]},{"i":{"x":[0.667],"y":[1]},"o":{"x":[0.333],"y":[0]},"t":89,"s":[20]},{"t":129,"s":[0]}]},"p":{"a":1,"k":[{"i":{"x":0.667,"y":1},"o":{"x":0.333,"y":0},"t":-41,"s":[523,1014,0],"to":[0,0,0],"ti":[0,0,0]},{"i":{"x":0.667,"y":1},"o":{"x":0.333,"y":0},"t":-1,"s":[523,1116,0],"to":[0,0,0],"ti":[0,0,0]},{"i":{"x":0.667,"y":1},"o":{"x":0.333,"y":0},"t":39,"s":[523,1014,0],"to":[0,0,0],"ti":[0,0,0]},{"i":{"x":0.667,"y":1},"o":{"x":0.333,"y":0},"t":79,"s":[523,1116,0],"to":[0,0,0],"ti":[0,0,0]},{"t":119,"s":[523,1014,0]}]},"a":{"a":0,"k":[-277.585,253.141,0]},"s":{"a":0,"k":[100,100,100]}},"ao":0,"shapes":[{"ty":"gr","it":[{"ind":0,"ty":"sh","ks":{"a":0,"k":{"i":[[1.87,-0.726],[0,0],[0.726,1.87],[0,0],[0,0],[0,0]],"o":[[0,0],[-1.87,0.726],[0,0],[0,0],[0,0],[0.726,1.87]],"v":[[-260.458,230.157],[-260.458,230.157],[-265.157,228.087],[-291.142,161.167],[-284.372,158.538],[-258.387,225.458]],"c":true}},"nm":"Path 1","hd":false},{"ty":"fl","c":{"a":0,"k":[0.063,0,0.361]},"o":{"a":0,"k":100},"r":1,"bm":0,"nm":"Fill 1","hd":false},{"ty":"tr","p":{"a":0,"k":[0,0]},"a":{"a":0,"k":[0,0]},"s":{"a":0,"k":[100,100]},"r":{"a":0,"k":0},"o":{"a":0,"k":100},"sk":{"a":0,"k":0},"sa":{"a":0,"k":0},"nm":"Transform"}],"nm":"Group 1","bm":0,"hd":false},{"ty":"gr","it":[{"ind":0,"ty":"sh","ks":{"a":0,"k":{"i":[[0,0],[0,0],[0,0],[0,0]],"o":[[0,0],[0,0],[0,0],[0,0]],"v":[[-281.386,166.228],[-294.926,171.485],[-297.912,163.796],[-284.372,158.538]],"c":true}},"nm":"Path 1","hd":false},{"ty":"fl","c":{"a":0,"k":[0.984313726425,0.878431379795,0.831372559071,1]},"o":{"a":0,"k":100},"r":1,"bm":0,"nm":"Fill 1","hd":false},{"ty":"tr","p":{"a":0,"k":[0,0]},"a":{"a":0,"k":[0,0]},"s":{"a":0,"k":[100,100]},"r":{"a":0,"k":0},"o":{"a":0,"k":100},"sk":{"a":0,"k":0},"sa":{"a":0,"k":0},"nm":"Transform"}],"nm":"Group 2","bm":0,"hd":false},{"ty":"gr","it":[{"ind":0,"ty":"sh","ks":{"a":0,"k":{"i":[[0,0],[0,0],[0,0],[-5.94,2.307],[0,0],[2.307,5.94]],"o":[[0,0],[0,0],[2.307,5.94],[0,0],[5.94,-2.307],[0,0]],"v":[[-241.98,307.84],[-263.49,316.193],[-254.175,340.183],[-239.243,346.762],[-239.243,346.762],[-232.664,331.831]],"c":true}},"nm":"Path 1","hd":false},{"ty":"fl","c":{"a":0,"k":[0.984313726425,0.878431379795,0.831372559071,1]},"o":{"a":0,"k":100},"r":1,"bm":0,"nm":"Fill 1","hd":false},{"ty":"tr","p":{"a":0,"k":[0,0]},"a":{"a":0,"k":[0,0]},"s":{"a":0,"k":[100,100]},"r":{"a":0,"k":0},"o":{"a":0,"k":100},"sk":{"a":0,"k":0},"sa":{"a":0,"k":0},"nm":"Transform"}],"nm":"Group 3","bm":0,"hd":false},{"ty":"gr","it":[{"ind":0,"ty":"sh","ks":{"a":0,"k":{"i":[[0,0],[0,0],[0,0],[-5.94,2.307],[0,0],[-2.307,-5.94]],"o":[[0,0],[0,0],[-2.307,-5.94],[0,0],[5.94,-2.307],[0,0]],"v":[[-241.98,307.84],[-263.49,316.193],[-322.506,164.21],[-315.927,149.278],[-315.927,149.278],[-300.995,155.857]],"c":true}},"nm":"Path 1","hd":false},{"ty":"fl","c":{"a":0,"k":[0.063,0,0.361]},"o":{"a":0,"k":100},"r":1,"bm":0,"nm":"Fill 1","hd":false},{"ty":"tr","p":{"a":0,"k":[0,0]},"a":{"a":0,"k":[0,0]},"s":{"a":0,"k":[100,100]},"r":{"a":0,"k":0},"o":{"a":0,"k":100},"sk":{"a":0,"k":0},"sa":{"a":0,"k":0},"nm":"Transform"}],"nm":"Group 4","bm":0,"hd":false},{"ty":"gr","it":[{"ind":0,"ty":"sh","ks":{"a":0,"k":{"i":[[0,0],[0,0],[0,0],[-1.1,0.427],[0,0],[0.427,1.1]],"o":[[0,0],[0,0],[0.427,1.1],[0,0],[1.1,-0.427],[0,0]],"v":[[-238.229,343.471],[-242.213,345.018],[-237.783,356.425],[-235.018,357.644],[-235.018,357.644],[-233.799,354.878]],"c":true}},"nm":"Path 1","hd":false},{"ty":"fl","c":{"a":0,"k":[0.063,0,0.361]},"o":{"a":0,"k":100},"r":1,"bm":0,"nm":"Fill 1","hd":false},{"ty":"tr","p":{"a":0,"k":[0,0]},"a":{"a":0,"k":[0,0]},"s":{"a":0,"k":[100,100]},"r":{"a":0,"k":0},"o":{"a":0,"k":100},"sk":{"a":0,"k":0},"sa":{"a":0,"k":0},"nm":"Transform"}],"nm":"Group 5","bm":0,"hd":false}],"ip":-41,"op":109,"st":-41,"ct":1,"bm":0},{"ddd":0,"ind":4,"ty":4,"nm":"B 3","sr":1,"ks":{"o":{"a":0,"k":100},"r":{"a":1,"k":[{"i":{"x":[0.667],"y":[1]},"o":{"x":[0.333],"y":[0]},"t":1,"s":[0]},{"i":{"x":[0.667],"y":[1]},"o":{"x":[0.333],"y":[0]},"t":41,"s":[-16]},{"i":{"x":[0.667],"y":[1]},"o":{"x":[0.333],"y":[0]},"t":81,"s":[0]},{"i":{"x":[0.667],"y":[1]},"o":{"x":[0.333],"y":[0]},"t":121,"s":[-16]},{"t":161,"s":[0]}]},"p":{"a":1,"k":[{"i":{"x":0.667,"y":1},"o":{"x":0.333,"y":0},"t":-9,"s":[719.716,742.032,0],"to":[0,0,0],"ti":[0,0,0]},{"i":{"x":0.667,"y":1},"o":{"x":0.333,"y":0},"t":31,"s":[719.716,766.032,0],"to":[0,0,0],"ti":[0,0,0]},{"i":{"x":0.667,"y":1},"o":{"x":0.333,"y":0},"t":71,"s":[719.716,742.032,0],"to":[0,0,0],"ti":[0,0,0]},{"i":{"x":0.667,"y":1},"o":{"x":0.333,"y":0},"t":111,"s":[719.716,766.032,0],"to":[0,0,0],"ti":[0,0,0]},{"t":151,"s":[719.716,742.032,0]}]},"a":{"a":0,"k":[-111.272,-84.552,0]},"s":{"a":0,"k":[80,80,100]}},"ao":0,"shapes":[{"ty":"gr","it":[{"ty":"gr","it":[{"ty":"gr","it":[{"ind":0,"ty":"sh","ks":{"a":0,"k":{"i":[[4.789,0],[0,4.789],[-27.17,0],[-8.596,-16.088],[4.224,-2.257],[2.257,4.223],[11.814,0],[0,-17.608]],"o":[[-4.789,0],[0,-27.171],[18.227,0],[2.257,4.224],[-4.223,2.257],[-5.574,-10.433],[-17.608,0],[0,4.789]],"v":[[-342.219,-106.345],[-350.89,-115.016],[-301.615,-164.292],[-258.129,-138.209],[-261.691,-126.475],[-273.425,-130.036],[-301.615,-146.949],[-333.547,-115.016]],"c":true}},"nm":"Path 1","hd":false},{"ty":"fl","c":{"a":0,"k":[0.063,0,0.361]},"o":{"a":0,"k":100},"r":1,"bm":0,"nm":"Fill 1","hd":false},{"ty":"tr","p":{"a":0,"k":[0,0]},"a":{"a":0,"k":[0,0]},"s":{"a":0,"k":[100,100]},"r":{"a":0,"k":0},"o":{"a":0,"k":100},"sk":{"a":0,"k":0},"sa":{"a":0,"k":0},"nm":"Transform"}],"nm":"Group 1","bm":0,"hd":false},{"ty":"tr","p":{"a":0,"k":[0,0]},"a":{"a":0,"k":[0,0]},"s":{"a":0,"k":[100,100]},"r":{"a":0,"k":0},"o":{"a":0,"k":100},"sk":{"a":0,"k":0},"sa":{"a":0,"k":0},"nm":"Transform"}],"nm":"Group 1","bm":0,"hd":false},{"ty":"gr","it":[{"ty":"gr","it":[{"ind":0,"ty":"sh","ks":{"a":0,"k":{"i":[[4.789,0],[0,4.789],[-27.17,0],[-8.596,-16.089],[4.224,-2.257],[2.257,4.226],[11.814,0],[0,-17.608]],"o":[[-4.789,0],[0,-27.171],[18.228,0],[2.256,4.224],[-4.222,2.256],[-5.573,-10.432],[-17.608,0],[0,4.789]],"v":[[-277.279,-12.288],[-285.95,-20.959],[-236.675,-70.234],[-193.189,-44.151],[-196.752,-32.416],[-208.486,-35.979],[-236.675,-52.892],[-268.607,-20.959]],"c":true}},"nm":"Path 1","hd":false},{"ty":"fl","c":{"a":0,"k":[0.063,0,0.361]},"o":{"a":0,"k":100},"r":1,"bm":0,"nm":"Fill 1","hd":false},{"ty":"tr","p":{"a":0,"k":[0,0]},"a":{"a":0,"k":[0,0]},"s":{"a":0,"k":[100,100]},"r":{"a":0,"k":0},"o":{"a":0,"k":100},"sk":{"a":0,"k":0},"sa":{"a":0,"k":0},"nm":"Transform"}],"nm":"Group 1","bm":0,"hd":false},{"ty":"tr","p":{"a":0,"k":[0,0]},"a":{"a":0,"k":[0,0]},"s":{"a":0,"k":[100,100]},"r":{"a":0,"k":0},"o":{"a":0,"k":100},"sk":{"a":0,"k":0},"sa":{"a":0,"k":0},"nm":"Transform"}],"nm":"Group 2","bm":0,"hd":false},{"ty":"tr","p":{"a":0,"k":[0,0]},"a":{"a":0,"k":[0,0]},"s":{"a":0,"k":[100,100]},"r":{"a":0,"k":0},"o":{"a":0,"k":100},"sk":{"a":0,"k":0},"sa":{"a":0,"k":0},"nm":"Transform"}],"nm":"Group 1","bm":0,"hd":false},{"ty":"gr","it":[{"ty":"gr","it":[{"ind":0,"ty":"sh","ks":{"a":0,"k":{"i":[[0.638,1.003],[0,0],[0,0],[0.056,0.079],[0,0],[0,0],[2.351,0],[0,0],[0,-3.574],[-1.105,-1.161],[0,0],[0,0],[-0.167,-0.214],[0,0],[0,0],[-2.049,0],[0,0],[0,3.574]],"o":[[0,0],[0,0],[-0.053,-0.082],[0,0],[0,0],[-1.133,-1.876],[0,0],[-3.574,0],[0,1.729],[0,0],[0,0],[0.14,0.234],[0,0],[0,0],[1.186,1.486],[0,0],[3.574,0],[0,-1.276]],"v":[[-25.22,-135.734],[-25.219,-135.736],[-25.246,-135.776],[-25.41,-136.017],[-51.758,-174.57],[-51.761,-174.562],[-57.297,-177.696],[-242.101,-177.696],[-248.572,-171.225],[-246.785,-166.768],[-246.786,-166.765],[-221.037,-128.962],[-220.577,-128.288],[-220.541,-128.236],[-220.54,-128.238],[-215.482,-125.797],[-30.679,-125.797],[-24.208,-132.268]],"c":true}},"nm":"Path 1","hd":false},{"ty":"fl","c":{"a":0,"k":[0.984313726425,0.878431379795,0.831372559071,1]},"o":{"a":0,"k":100},"r":1,"bm":0,"nm":"Fill 1","hd":false},{"ty":"tr","p":{"a":0,"k":[0,0]},"a":{"a":0,"k":[0,0]},"s":{"a":0,"k":[100,100]},"r":{"a":0,"k":0},"o":{"a":0,"k":100},"sk":{"a":0,"k":0},"sa":{"a":0,"k":0},"nm":"Transform"}],"nm":"Group 1","bm":0,"hd":false},{"ty":"gr","it":[{"ind":0,"ty":"sh","ks":{"a":0,"k":{"i":[[1.134,1.782],[0,0],[0,0],[0.1,0.14],[0,0],[0,0],[4.18,0],[0,0],[0,-6.354],[-1.964,-2.064],[0,0],[0,0],[-0.298,-0.38],[0,0],[0,0],[-3.643,0],[0,0],[0,6.354]],"o":[[0,0],[0,0],[-0.094,-0.145],[0,0],[0,0],[-2.014,-3.335],[0,0],[-6.354,0],[0,3.074],[0,0],[0,0],[0.249,0.417],[0,0],[0,0],[2.108,2.642],[0,0],[6.354,0],[0,-2.269]],"v":[[131.027,-21.248],[131.03,-21.252],[130.981,-21.324],[130.689,-21.751],[-5.466,-220.893],[-5.47,-220.879],[-15.314,-226.451],[-343.866,-226.451],[-355.37,-214.946],[-352.193,-207.023],[-352.195,-207.017],[-217.105,-9.208],[-216.288,-8.011],[-216.224,-7.917],[-216.222,-7.922],[-207.229,-3.582],[121.323,-3.582],[132.827,-15.087]],"c":true}},"nm":"Path 1","hd":false},{"ty":"fl","c":{"a":0,"k":[0.106,0.925,0.114]},"o":{"a":0,"k":100},"r":1,"bm":0,"nm":"Fill 1","hd":false},{"ty":"tr","p":{"a":0,"k":[0,0]},"a":{"a":0,"k":[0,0]},"s":{"a":0,"k":[100,100]},"r":{"a":0,"k":0},"o":{"a":0,"k":100},"sk":{"a":0,"k":0},"sa":{"a":0,"k":0},"nm":"Transform"}],"nm":"Group 2","bm":0,"hd":false},{"ty":"gr","it":[{"ind":0,"ty":"sh","ks":{"a":0,"k":{"i":[[0,0],[0,0],[0,0],[0,0],[0,0],[0,0],[0,0]],"o":[[0,0],[0,0],[0,0],[0,0],[0,0],[0,0],[0,0]],"v":[[-207.229,-3.582],[-210.692,-3.582],[-347.328,-203.442],[-347.328,-165.522],[-210.692,34.338],[124.785,34.338],[124.785,-3.582]],"c":true}},"nm":"Path 1","hd":false},{"ty":"fl","c":{"a":0,"k":[0.984313726425,0.878431379795,0.831372559071,1]},"o":{"a":0,"k":100},"r":1,"bm":0,"nm":"Fill 1","hd":false},{"ty":"tr","p":{"a":0,"k":[0,0]},"a":{"a":0,"k":[0,0]},"s":{"a":0,"k":[100,100]},"r":{"a":0,"k":0},"o":{"a":0,"k":100},"sk":{"a":0,"k":0},"sa":{"a":0,"k":0},"nm":"Transform"}],"nm":"Group 3","bm":0,"hd":false},{"ty":"gr","it":[{"ind":0,"ty":"sh","ks":{"a":0,"k":{"i":[[6.354,0],[0,0],[1.145,-0.382],[0,0],[0,0],[0,0],[1.004,-0.286],[0,0],[0,0],[0,-5.256],[0,0],[-1.964,-2.064],[0,0],[0,0],[-0.298,-0.38],[0,0],[0,0],[-3.643,0],[0,0],[0,6.354]],"o":[[0,0],[-1.273,0],[0,0],[0,0],[0,0],[-1.096,0],[0,0],[0,0],[-4.814,1.375],[0,0],[0,3.074],[0,0],[0,0],[0.249,0.417],[0,0],[0,0],[2.108,2.643],[0,0],[6.354,0],[0,-6.354]],"v":[[121.323,34.338],[-207.229,34.338],[-210.869,34.935],[-210.692,34.338],[-343.866,-160.457],[-343.866,-165.522],[-347.021,-165.073],[-347.026,-165.079],[-347.028,-165.071],[-355.37,-154.017],[-355.37,-154.017],[-352.193,-146.095],[-352.195,-146.088],[-217.105,51.721],[-216.288,52.919],[-216.224,53.012],[-216.222,53.006],[-207.229,57.347],[121.323,57.347],[132.827,45.843]],"c":true}},"nm":"Path 1","hd":false},{"ty":"fl","c":{"a":0,"k":[0.106,0.925,0.114]},"o":{"a":0,"k":100},"r":1,"bm":0,"nm":"Fill 1","hd":false},{"ty":"tr","p":{"a":0,"k":[0,0]},"a":{"a":0,"k":[0,0]},"s":{"a":0,"k":[100,100]},"r":{"a":0,"k":0},"o":{"a":0,"k":100},"sk":{"a":0,"k":0},"sa":{"a":0,"k":0},"nm":"Transform"}],"nm":"Group 4","bm":0,"hd":false},{"ty":"tr","p":{"a":0,"k":[0,0]},"a":{"a":0,"k":[0,0]},"s":{"a":0,"k":[100,100]},"r":{"a":0,"k":0},"o":{"a":0,"k":100},"sk":{"a":0,"k":0},"sa":{"a":0,"k":0},"nm":"Transform"}],"nm":"Group 2","bm":0,"hd":false},{"ty":"gr","it":[{"ty":"gr","it":[{"ty":"gr","it":[{"ind":0,"ty":"sh","ks":{"a":0,"k":{"i":[[4.789,0],[0,27.171],[-4.789,0],[0,-4.789],[-17.608,0],[0,-4.789]],"o":[[-27.17,0],[0,-4.789],[4.789,0],[0,17.608],[4.789,0],[0,4.789]],"v":[[-301.615,-65.741],[-350.89,-115.016],[-342.219,-123.688],[-333.547,-115.016],[-301.615,-83.084],[-292.944,-74.412]],"c":true}},"nm":"Path 1","hd":false},{"ty":"fl","c":{"a":0,"k":[0.063,0,0.361]},"o":{"a":0,"k":100},"r":1,"bm":0,"nm":"Fill 1","hd":false},{"ty":"tr","p":{"a":0,"k":[0,0]},"a":{"a":0,"k":[0,0]},"s":{"a":0,"k":[100,100]},"r":{"a":0,"k":0},"o":{"a":0,"k":100},"sk":{"a":0,"k":0},"sa":{"a":0,"k":0},"nm":"Transform"}],"nm":"Group 1","bm":0,"hd":false},{"ty":"tr","p":{"a":0,"k":[0,0]},"a":{"a":0,"k":[0,0]},"s":{"a":0,"k":[100,100]},"r":{"a":0,"k":0},"o":{"a":0,"k":100},"sk":{"a":0,"k":0},"sa":{"a":0,"k":0},"nm":"Transform"}],"nm":"Group 1","bm":0,"hd":false},{"ty":"gr","it":[{"ty":"gr","it":[{"ind":0,"ty":"sh","ks":{"a":0,"k":{"i":[[4.789,0],[0,27.17],[-4.789,0],[0,-4.789],[-17.608,0],[0,-4.789]],"o":[[-27.17,0],[0,-4.789],[4.789,0],[0,17.608],[4.789,0],[0,4.789]],"v":[[-236.675,28.316],[-285.95,-20.959],[-277.279,-29.63],[-268.607,-20.959],[-236.675,10.973],[-228.004,19.645]],"c":true}},"nm":"Path 1","hd":false},{"ty":"fl","c":{"a":0,"k":[0.063,0,0.361]},"o":{"a":0,"k":100},"r":1,"bm":0,"nm":"Fill 1","hd":false},{"ty":"tr","p":{"a":0,"k":[0,0]},"a":{"a":0,"k":[0,0]},"s":{"a":0,"k":[100,100]},"r":{"a":0,"k":0},"o":{"a":0,"k":100},"sk":{"a":0,"k":0},"sa":{"a":0,"k":0},"nm":"Transform"}],"nm":"Group 1","bm":0,"hd":false},{"ty":"tr","p":{"a":0,"k":[0,0]},"a":{"a":0,"k":[0,0]},"s":{"a":0,"k":[100,100]},"r":{"a":0,"k":0},"o":{"a":0,"k":100},"sk":{"a":0,"k":0},"sa":{"a":0,"k":0},"nm":"Transform"}],"nm":"Group 2","bm":0,"hd":false},{"ty":"tr","p":{"a":0,"k":[0,0]},"a":{"a":0,"k":[0,0]},"s":{"a":0,"k":[100,100]},"r":{"a":0,"k":0},"o":{"a":0,"k":100},"sk":{"a":0,"k":0},"sa":{"a":0,"k":0},"nm":"Transform"}],"nm":"Group 3","bm":0,"hd":false}],"ip":-9,"op":141,"st":-9,"ct":1,"bm":0},{"ddd":0,"ind":5,"ty":4,"nm":"B 2","sr":1,"ks":{"o":{"a":0,"k":100},"r":{"a":1,"k":[{"i":{"x":[0.667],"y":[1]},"o":{"x":[0.333],"y":[0]},"t":-36,"s":[-20]},{"i":{"x":[0.667],"y":[1]},"o":{"x":[0.333],"y":[0]},"t":4,"s":[-6]},{"i":{"x":[0.667],"y":[1]},"o":{"x":[0.333],"y":[0]},"t":44,"s":[-20]},{"i":{"x":[0.667],"y":[1]},"o":{"x":[0.333],"y":[0]},"t":84,"s":[-6]},{"t":124,"s":[-20]}]},"p":{"a":1,"k":[{"i":{"x":0.667,"y":1},"o":{"x":0.333,"y":0},"t":-46,"s":[934.067,909.098,0],"to":[0,0,0],"ti":[0,0,0]},{"i":{"x":0.667,"y":1},"o":{"x":0.333,"y":0},"t":-6,"s":[947.748,946.686,0],"to":[0,0,0],"ti":[0,0,0]},{"i":{"x":0.667,"y":1},"o":{"x":0.333,"y":0},"t":34,"s":[934.067,909.098,0],"to":[0,0,0],"ti":[0,0,0]},{"i":{"x":0.667,"y":1},"o":{"x":0.333,"y":0},"t":74,"s":[947.748,946.686,0],"to":[0,0,0],"ti":[0,0,0]},{"t":114,"s":[934.067,909.098,0]}]},"a":{"a":0,"k":[170.905,97.403,0]},"s":{"a":0,"k":[80,80,100]}},"ao":0,"shapes":[{"ty":"gr","it":[{"ind":0,"ty":"sh","ks":{"a":0,"k":{"i":[[0,0],[0,0],[0,0],[0,0]],"o":[[0,0],[0,0],[0,0],[0,0]],"v":[[19.845,169.822],[-51.67,-135.022],[-67.292,-79.52],[4.223,225.324]],"c":true}},"nm":"Path 1","hd":false},{"ty":"fl","c":{"a":0,"k":[0.984313726425,0.878431379795,0.831372559071,1]},"o":{"a":0,"k":100},"r":1,"bm":0,"nm":"Fill 1","hd":false},{"ty":"tr","p":{"a":0,"k":[0,0]},"a":{"a":0,"k":[0,0]},"s":{"a":0,"k":[100,100]},"r":{"a":0,"k":0},"o":{"a":0,"k":100},"sk":{"a":0,"k":0},"sa":{"a":0,"k":0},"nm":"Transform"}],"nm":"Group 1","bm":0,"hd":false},{"ty":"gr","it":[{"ty":"gr","it":[{"ty":"gr","it":[{"ind":0,"ty":"sh","ks":{"a":0,"k":{"i":[[0,0],[0,0],[-4.314,15.327],[0,0],[15.327,4.314],[0,0]],"o":[[0,0],[15.326,4.314],[0,0],[4.314,-15.327],[0,0],[0,0]],"v":[[4.223,225.324],[359.902,325.436],[395.464,305.496],[395.464,305.496],[375.524,269.933],[19.845,169.822]],"c":true}},"nm":"Path 1","hd":false},{"ty":"fl","c":{"a":0,"k":[0.984313726425,0.878431379795,0.831372559071,1]},"o":{"a":0,"k":100},"r":1,"bm":0,"nm":"Fill 1","hd":false},{"ty":"tr","p":{"a":0,"k":[0,0]},"a":{"a":0,"k":[0,0]},"s":{"a":0,"k":[100,100]},"r":{"a":0,"k":0},"o":{"a":0,"k":100},"sk":{"a":0,"k":0},"sa":{"a":0,"k":0},"nm":"Transform"}],"nm":"Group 1","bm":0,"hd":false},{"ty":"gr","it":[{"ind":0,"ty":"sh","ks":{"a":0,"k":{"i":[[0,0],[-1.651,5.867],[0,0],[22.391,6.302],[0,0],[0,0]],"o":[[3.659,-4.404],[0,0],[6.302,-22.391],[0,0],[0,0],[0,0]],"v":[[402.514,325.263],[410.641,309.767],[410.641,309.767],[381.51,257.813],[23.445,157.03],[-46.462,-140.963]],"c":false}},"nm":"Path 1","hd":false},{"ty":"st","c":{"a":0,"k":[1,1,1,1]},"o":{"a":0,"k":100},"w":{"a":0,"k":2},"lc":2,"lj":2,"bm":0,"nm":"Stroke 1","hd":false},{"ty":"tr","p":{"a":0,"k":[0,0]},"a":{"a":0,"k":[0,0]},"s":{"a":0,"k":[100,100]},"r":{"a":0,"k":0},"o":{"a":0,"k":100},"sk":{"a":0,"k":0},"sa":{"a":0,"k":0},"nm":"Transform"}],"nm":"Group 2","bm":0,"hd":false},{"ty":"gr","it":[{"ind":0,"ty":"sh","ks":{"a":0,"k":{"i":[[0,0],[0,0],[-6.302,22.391],[0,0],[22.391,6.302],[0,0]],"o":[[0,0],[22.391,6.302],[0,0],[6.302,-22.391],[0,0],[0,0]],"v":[[0.622,238.116],[358.687,338.899],[410.641,309.767],[410.641,309.767],[381.51,257.813],[23.445,157.03]],"c":true}},"nm":"Path 1","hd":false},{"ty":"fl","c":{"a":0,"k":[0.043,0.451,0.682]},"o":{"a":0,"k":100},"r":1,"bm":0,"nm":"Fill 1","hd":false},{"ty":"tr","p":{"a":0,"k":[0,0]},"a":{"a":0,"k":[0,0]},"s":{"a":0,"k":[100,100]},"r":{"a":0,"k":0},"o":{"a":0,"k":100},"sk":{"a":0,"k":0},"sa":{"a":0,"k":0},"nm":"Transform"}],"nm":"Group 3","bm":0,"hd":false},{"ty":"tr","p":{"a":0,"k":[0,0]},"a":{"a":0,"k":[0,0]},"s":{"a":0,"k":[100,100]},"r":{"a":0,"k":0},"o":{"a":0,"k":100},"sk":{"a":0,"k":0},"sa":{"a":0,"k":0},"nm":"Transform"}],"nm":"Group 1","bm":0,"hd":false},{"ty":"tr","p":{"a":0,"k":[0,0]},"a":{"a":0,"k":[0,0]},"s":{"a":0,"k":[100,100]},"r":{"a":0,"k":0},"o":{"a":0,"k":100},"sk":{"a":0,"k":0},"sa":{"a":0,"k":0},"nm":"Transform"}],"nm":"Group 2","bm":0,"hd":false},{"ty":"gr","it":[{"ind":0,"ty":"sh","ks":{"a":0,"k":{"i":[[0,0],[0,0],[15.636,4.401],[0,0],[1.369,-4.865],[0,0],[-0.566,-2.412],[0,0],[0,0]],"o":[[0,0],[-3.115,-14.869],[0,0],[-4.865,-1.369],[0,0],[-0.671,2.385],[0,0],[0,0],[0,0]],"v":[[339.822,-15.09],[339.812,-15.089],[309.995,-47.031],[-39.261,-145.335],[-50.549,-139.006],[-69.869,-70.363],[-70.03,-63.051],[0.622,238.116],[411.082,288.624]],"c":true}},"nm":"Path 1","hd":false},{"ty":"fl","c":{"a":0,"k":[0.043,0.451,0.682]},"o":{"a":0,"k":100},"r":1,"bm":0,"nm":"Fill 1","hd":false},{"ty":"tr","p":{"a":0,"k":[0,0]},"a":{"a":0,"k":[0,0]},"s":{"a":0,"k":[100,100]},"r":{"a":0,"k":0},"o":{"a":0,"k":100},"sk":{"a":0,"k":0},"sa":{"a":0,"k":0},"nm":"Transform"}],"nm":"Group 3","bm":0,"hd":false}],"ip":-46,"op":104,"st":-46,"ct":1,"bm":0},{"ddd":0,"ind":6,"ty":4,"nm":"B 1","sr":1,"ks":{"o":{"a":0,"k":100},"r":{"a":1,"k":[{"i":{"x":[0.667],"y":[1]},"o":{"x":[0.333],"y":[0]},"t":-37,"s":[0]},{"i":{"x":[0.667],"y":[1]},"o":{"x":[0.333],"y":[0]},"t":3,"s":[11]},{"i":{"x":[0.667],"y":[1]},"o":{"x":[0.333],"y":[0]},"t":43,"s":[0]},{"i":{"x":[0.667],"y":[1]},"o":{"x":[0.333],"y":[0]},"t":83,"s":[11]},{"t":123,"s":[0]}]},"p":{"a":1,"k":[{"i":{"x":0.667,"y":1},"o":{"x":0.333,"y":0},"t":-47,"s":[793.316,1089.232,0],"to":[0,0,0],"ti":[0,0,0]},{"i":{"x":0.667,"y":1},"o":{"x":0.333,"y":0},"t":-7,"s":[793.316,1047.632,0],"to":[0,0,0],"ti":[0,0,0]},{"i":{"x":0.667,"y":1},"o":{"x":0.333,"y":0},"t":33,"s":[793.316,1089.232,0],"to":[0,0,0],"ti":[0,0,0]},{"i":{"x":0.667,"y":1},"o":{"x":0.333,"y":0},"t":73,"s":[793.316,1047.632,0],"to":[0,0,0],"ti":[0,0,0]},{"t":113,"s":[793.316,1089.232,0]}]},"a":{"a":0,"k":[-14.928,289.407,0]},"s":{"a":0,"k":[80,80,100]}},"ao":0,"shapes":[{"ty":"gr","it":[{"ty":"gr","it":[{"ind":0,"ty":"sh","ks":{"a":0,"k":{"i":[[0,0],[0,0],[4.172,15.366],[0,0],[-15.366,4.172],[0,0]],"o":[[0,0],[-15.366,4.172],[0,0],[-4.172,-15.366],[0,0],[0,0]],"v":[[274.961,374.126],[-81.63,470.94],[-117.006,450.671],[-117.006,450.671],[-96.738,415.295],[259.854,318.481]],"c":true}},"nm":"Path 1","hd":false},{"ty":"fl","c":{"a":0,"k":[0.984313726425,0.878431379795,0.831372559071,1]},"o":{"a":0,"k":100},"r":1,"bm":0,"nm":"Fill 1","hd":false},{"ty":"tr","p":{"a":0,"k":[0,0]},"a":{"a":0,"k":[0,0]},"s":{"a":0,"k":[100,100]},"r":{"a":0,"k":0},"o":{"a":0,"k":100},"sk":{"a":0,"k":0},"sa":{"a":0,"k":0},"nm":"Transform"}],"nm":"Group 1","bm":0,"hd":false},{"ty":"gr","it":[{"ind":0,"ty":"sh","ks":{"a":0,"k":{"i":[[0,0],[1.597,5.882],[0,0],[-22.449,6.095],[0,0]],"o":[[-3.618,-4.437],[0,0],[-6.095,-22.449],[0,0],[0,0]],"v":[[-124.239,470.373],[-132.222,454.802],[-132.222,454.802],[-102.61,403.12],[256.372,305.657]],"c":false}},"nm":"Path 1","hd":false},{"ty":"st","c":{"a":0,"k":[1,1,1,1]},"o":{"a":0,"k":100},"w":{"a":0,"k":2},"lc":2,"lj":2,"bm":0,"nm":"Stroke 1","hd":false},{"ty":"tr","p":{"a":0,"k":[0,0]},"a":{"a":0,"k":[0,0]},"s":{"a":0,"k":[100,100]},"r":{"a":0,"k":0},"o":{"a":0,"k":100},"sk":{"a":0,"k":0},"sa":{"a":0,"k":0},"nm":"Transform"}],"nm":"Group 2","bm":0,"hd":false},{"ty":"gr","it":[{"ind":0,"ty":"sh","ks":{"a":0,"k":{"i":[[3.099,-0.841],[0,0],[6.095,22.449],[0,0],[-22.449,6.095],[0,0],[0,0]],"o":[[0,0],[-22.449,6.095],[0,0],[-6.095,-22.449],[0,0],[0,0],[0.841,3.099]],"v":[[272.832,388.474],[-80.539,484.414],[-132.222,454.802],[-132.222,454.802],[-102.61,403.12],[256.372,305.657],[276.919,381.339]],"c":true}},"nm":"Path 1","hd":false},{"ty":"fl","c":{"a":0,"k":[0.612,0.733,0.984]},"o":{"a":0,"k":100},"r":1,"bm":0,"nm":"Fill 1","hd":false},{"ty":"tr","p":{"a":0,"k":[0,0]},"a":{"a":0,"k":[0,0]},"s":{"a":0,"k":[100,100]},"r":{"a":0,"k":0},"o":{"a":0,"k":100},"sk":{"a":0,"k":0},"sa":{"a":0,"k":0},"nm":"Transform"}],"nm":"Group 3","bm":0,"hd":false},{"ty":"tr","p":{"a":0,"k":[0,0]},"a":{"a":0,"k":[0,0]},"s":{"a":0,"k":[100,100]},"r":{"a":0,"k":0},"o":{"a":0,"k":100},"sk":{"a":0,"k":0},"sa":{"a":0,"k":0},"nm":"Transform"}],"nm":"Group 1","bm":0,"hd":false},{"ty":"gr","it":[{"ind":0,"ty":"sh","ks":{"a":0,"k":{"i":[[0,0],[0,0],[6.92,-1.879],[0,0],[-6.095,-22.449],[0,0],[-3.97,-4.612],[0,0]],"o":[[0,0],[-4.497,-5.585],[0,0],[-22.449,6.095],[0,0],[1.701,6.264],[0,0],[0,0]],"v":[[256.372,305.657],[90.499,99.65],[71.705,93.549],[-275.886,187.92],[-305.497,239.602],[-305.497,239.602],[-296.796,256.024],[-124.236,470.371]],"c":true}},"nm":"Path 1","hd":false},{"ty":"fl","c":{"a":0,"k":[0.612,0.733,0.984]},"o":{"a":0,"k":100},"r":1,"bm":0,"nm":"Fill 1","hd":false},{"ty":"tr","p":{"a":0,"k":[0,0]},"a":{"a":0,"k":[0,0]},"s":{"a":0,"k":[100,100]},"r":{"a":0,"k":0},"o":{"a":0,"k":100},"sk":{"a":0,"k":0},"sa":{"a":0,"k":0},"nm":"Transform"}],"nm":"Group 2","bm":0,"hd":false}],"ip":-47,"op":103,"st":-47,"ct":1,"bm":0},{"ddd":0,"ind":7,"ty":4,"nm":"Line 3","sr":1,"ks":{"o":{"a":0,"k":100},"r":{"a":0,"k":0},"p":{"a":0,"k":[1229.783,927.32,0]},"a":{"a":0,"k":[404.833,440.11,0]},"s":{"a":0,"k":[80,80,100]}},"ao":0,"shapes":[{"ty":"gr","it":[{"ind":0,"ty":"sh","ks":{"a":0,"k":{"i":[[0,0],[39.22,-28.786],[2.71,17.131],[-11.999,-15.282],[21.894,-19.851]],"o":[[0,0],[-39.22,28.786],[-2.71,-17.131],[11.999,15.282],[0,0]],"v":[[452.642,372.868],[424.197,445.496],[356.032,442.601],[378.336,429.364],[355.707,507.352]],"c":false}},"nm":"Path 1","hd":false},{"ty":"st","c":{"a":0,"k":[0.984313726425,0.878431379795,0.831372559071,1]},"o":{"a":0,"k":100},"w":{"a":0,"k":2},"lc":2,"lj":2,"bm":0,"nm":"Stroke 1","hd":false},{"ty":"tr","p":{"a":0,"k":[0,0]},"a":{"a":0,"k":[0,0]},"s":{"a":0,"k":[100,100]},"r":{"a":0,"k":0},"o":{"a":0,"k":100},"sk":{"a":0,"k":0},"sa":{"a":0,"k":0},"nm":"Transform"}],"nm":"Group 1","bm":0,"hd":false},{"ty":"tm","s":{"a":1,"k":[{"i":{"x":[0.667],"y":[1]},"o":{"x":[0.167],"y":[0.167]},"t":55,"s":[0]},{"t":65,"s":[100]}]},"e":{"a":1,"k":[{"i":{"x":[0.667],"y":[1]},"o":{"x":[0.167],"y":[0.167]},"t":50,"s":[0]},{"t":60,"s":[100]}]},"o":{"a":0,"k":0},"m":1,"nm":"Trim In Path","hd":false}],"ip":50,"op":200,"st":50,"ct":1,"bm":0},{"ddd":0,"ind":8,"ty":4,"nm":"Line 2","sr":1,"ks":{"o":{"a":0,"k":100},"r":{"a":0,"k":0},"p":{"a":0,"k":[1229.783,927.32,0]},"a":{"a":0,"k":[404.833,440.11,0]},"s":{"a":0,"k":[80,80,100]}},"ao":0,"shapes":[{"ty":"gr","it":[{"ind":0,"ty":"sh","ks":{"a":0,"k":{"i":[[0,0],[39.22,-28.786],[2.71,17.131],[-11.999,-15.282],[21.894,-19.851]],"o":[[0,0],[-39.22,28.786],[-2.71,-17.131],[11.999,15.282],[0,0]],"v":[[452.642,372.868],[424.197,445.496],[356.032,442.601],[378.336,429.364],[355.707,507.352]],"c":false}},"nm":"Path 1","hd":false},{"ty":"st","c":{"a":0,"k":[0.984313726425,0.878431379795,0.831372559071,1]},"o":{"a":0,"k":100},"w":{"a":0,"k":2},"lc":2,"lj":2,"bm":0,"nm":"Stroke 1","hd":false},{"ty":"tr","p":{"a":0,"k":[0,0]},"a":{"a":0,"k":[0,0]},"s":{"a":0,"k":[100,100]},"r":{"a":0,"k":0},"o":{"a":0,"k":100},"sk":{"a":0,"k":0},"sa":{"a":0,"k":0},"nm":"Transform"}],"nm":"Group 1","bm":0,"hd":false},{"ty":"tm","s":{"a":1,"k":[{"i":{"x":[0.667],"y":[1]},"o":{"x":[0.167],"y":[0.167]},"t":29,"s":[0]},{"t":39,"s":[100]}]},"e":{"a":1,"k":[{"i":{"x":[0.667],"y":[1]},"o":{"x":[0.167],"y":[0.167]},"t":24,"s":[0]},{"t":34,"s":[100]}]},"o":{"a":0,"k":0},"m":1,"nm":"Trim In Path","hd":false}],"ip":24,"op":174,"st":24,"ct":1,"bm":0},{"ddd":0,"ind":9,"ty":4,"nm":"Line","sr":1,"ks":{"o":{"a":0,"k":100},"r":{"a":0,"k":0},"p":{"a":0,"k":[1229.783,927.32,0]},"a":{"a":0,"k":[404.833,440.11,0]},"s":{"a":0,"k":[80,80,100]}},"ao":0,"shapes":[{"ty":"gr","it":[{"ind":0,"ty":"sh","ks":{"a":0,"k":{"i":[[0,0],[39.22,-28.786],[2.71,17.131],[-11.999,-15.282],[21.894,-19.851]],"o":[[0,0],[-39.22,28.786],[-2.71,-17.131],[11.999,15.282],[0,0]],"v":[[452.642,372.868],[424.197,445.496],[356.032,442.601],[378.336,429.364],[355.707,507.352]],"c":false}},"nm":"Path 1","hd":false},{"ty":"st","c":{"a":0,"k":[0.984313726425,0.878431379795,0.831372559071,1]},"o":{"a":0,"k":100},"w":{"a":0,"k":2},"lc":2,"lj":2,"bm":0,"nm":"Stroke 1","hd":false},{"ty":"tr","p":{"a":0,"k":[0,0]},"a":{"a":0,"k":[0,0]},"s":{"a":0,"k":[100,100]},"r":{"a":0,"k":0},"o":{"a":0,"k":100},"sk":{"a":0,"k":0},"sa":{"a":0,"k":0},"nm":"Transform"}],"nm":"Group 1","bm":0,"hd":false},{"ty":"tm","s":{"a":1,"k":[{"i":{"x":[0.667],"y":[1]},"o":{"x":[0.167],"y":[0.167]},"t":5,"s":[0]},{"t":15,"s":[100]}]},"e":{"a":1,"k":[{"i":{"x":[0.667],"y":[1]},"o":{"x":[0.167],"y":[0.167]},"t":0,"s":[0]},{"t":10,"s":[100]}]},"o":{"a":0,"k":0},"m":1,"nm":"Trim In Path","hd":false}],"ip":0,"op":150,"st":0,"ct":1,"bm":0},{"ddd":0,"ind":10,"ty":4,"nm":"S 4","sr":1,"ks":{"o":{"a":1,"k":[{"i":{"x":[0.667],"y":[1]},"o":{"x":[0.333],"y":[0]},"t":66.667,"s":[100]},{"t":80,"s":[0]}]},"r":{"a":1,"k":[{"i":{"x":[0.667],"y":[1]},"o":{"x":[0.333],"y":[0]},"t":40,"s":[60]},{"t":80,"s":[0]}]},"p":{"a":0,"k":[530.38,487.057,0]},"a":{"a":0,"k":[-485.669,-261.469,0]},"s":{"a":1,"k":[{"i":{"x":[0.667,0.667,0.667],"y":[1,1,1]},"o":{"x":[0.333,0.333,0.333],"y":[0,0,0]},"t":40,"s":[0,0,100]},{"t":80,"s":[80,80,100]}]}},"ao":0,"shapes":[{"ty":"gr","it":[{"ind":0,"ty":"sh","ks":{"a":0,"k":{"i":[[1.709,2.483],[0,0],[-1.021,1.47],[0,0],[-1.711,-2.463],[0,0],[1.015,-1.474],[0,0]],"o":[[0,0],[-1.015,-1.474],[0,0],[1.711,-2.463],[0,0],[1.021,1.47],[0,0],[-1.709,2.483]],"v":[[-489.213,-228.082],[-510.613,-259.172],[-510.602,-264.065],[-489.202,-294.87],[-482.137,-294.87],[-460.736,-264.065],[-460.726,-259.172],[-482.126,-228.082]],"c":true}},"nm":"Path 1","hd":false},{"ty":"fl","c":{"a":0,"k":[0.612,0.733,0.984]},"o":{"a":0,"k":100},"r":1,"bm":0,"nm":"Fill 1","hd":false},{"ty":"tr","p":{"a":0,"k":[0,0]},"a":{"a":0,"k":[0,0]},"s":{"a":0,"k":[100,100]},"r":{"a":0,"k":0},"o":{"a":0,"k":100},"sk":{"a":0,"k":0},"sa":{"a":0,"k":0},"nm":"Transform"}],"nm":"Group 1","bm":0,"hd":false}],"ip":30,"op":180,"st":30,"ct":1,"bm":0},{"ddd":0,"ind":11,"ty":4,"nm":"S 3","sr":1,"ks":{"o":{"a":1,"k":[{"i":{"x":[0.667],"y":[1]},"o":{"x":[0.333],"y":[0]},"t":53.333,"s":[100]},{"t":66.6669921875,"s":[0]}]},"r":{"a":1,"k":[{"i":{"x":[0.667],"y":[1]},"o":{"x":[0.333],"y":[0]},"t":26.667,"s":[-60]},{"t":66.6669921875,"s":[0]}]},"p":{"a":0,"k":[1157.757,793.818,0]},"a":{"a":0,"k":[504.489,-82.705,0]},"s":{"a":1,"k":[{"i":{"x":[0.667,0.667,0.667],"y":[1,1,1]},"o":{"x":[0.333,0.333,0.333],"y":[0,0,0]},"t":26.667,"s":[0,0,100]},{"t":66.6669921875,"s":[80,80,100]}]}},"ao":0,"shapes":[{"ty":"gr","it":[{"ind":0,"ty":"sh","ks":{"a":0,"k":{"i":[[2.578,3.745],[0,0],[-1.54,2.217],[0,0],[-2.58,-3.714],[0,0],[1.53,-2.223],[0,0]],"o":[[0,0],[-1.53,-2.223],[0,0],[2.58,-3.714],[0,0],[1.54,2.217],[0,0],[-2.578,3.745]],"v":[[499.147,-51.905],[480.391,-79.152],[480.407,-86.53],[499.162,-113.529],[509.816,-113.529],[528.572,-86.53],[528.588,-79.152],[509.832,-51.905]],"c":true}},"nm":"Path 1","hd":false},{"ty":"fl","c":{"a":0,"k":[0.984313726425,0.878431379795,0.831372559071,1]},"o":{"a":0,"k":100},"r":1,"bm":0,"nm":"Fill 1","hd":false},{"ty":"tr","p":{"a":0,"k":[0,0]},"a":{"a":0,"k":[0,0]},"s":{"a":0,"k":[100,100]},"r":{"a":0,"k":0},"o":{"a":0,"k":100},"sk":{"a":0,"k":0},"sa":{"a":0,"k":0},"nm":"Transform"}],"nm":"Group 1","bm":0,"hd":false}],"ip":20,"op":170,"st":20,"ct":1,"bm":0},{"ddd":0,"ind":12,"ty":4,"nm":"S 2","sr":1,"ks":{"o":{"a":1,"k":[{"i":{"x":[0.667],"y":[1]},"o":{"x":[0.333],"y":[0]},"t":40,"s":[100]},{"t":53.3330078125,"s":[0]}]},"r":{"a":1,"k":[{"i":{"x":[0.667],"y":[1]},"o":{"x":[0.333],"y":[0]},"t":13.333,"s":[-60]},{"t":53.3330078125,"s":[0]}]},"p":{"a":0,"k":[530.38,487.057,0]},"a":{"a":0,"k":[-485.669,-261.469,0]},"s":{"a":1,"k":[{"i":{"x":[0.667,0.667,0.667],"y":[1,1,1]},"o":{"x":[0.333,0.333,0.333],"y":[0,0,0]},"t":13.333,"s":[0,0,100]},{"t":53.3330078125,"s":[80,80,100]}]}},"ao":0,"shapes":[{"ty":"gr","it":[{"ind":0,"ty":"sh","ks":{"a":0,"k":{"i":[[1.709,2.483],[0,0],[-1.021,1.47],[0,0],[-1.711,-2.463],[0,0],[1.015,-1.474],[0,0]],"o":[[0,0],[-1.015,-1.474],[0,0],[1.711,-2.463],[0,0],[1.021,1.47],[0,0],[-1.709,2.483]],"v":[[-489.213,-228.082],[-510.613,-259.172],[-510.602,-264.065],[-489.202,-294.87],[-482.137,-294.87],[-460.736,-264.065],[-460.726,-259.172],[-482.126,-228.082]],"c":true}},"nm":"Path 1","hd":false},{"ty":"fl","c":{"a":0,"k":[0.612,0.733,0.984]},"o":{"a":0,"k":100},"r":1,"bm":0,"nm":"Fill 1","hd":false},{"ty":"tr","p":{"a":0,"k":[0,0]},"a":{"a":0,"k":[0,0]},"s":{"a":0,"k":[100,100]},"r":{"a":0,"k":0},"o":{"a":0,"k":100},"sk":{"a":0,"k":0},"sa":{"a":0,"k":0},"nm":"Transform"}],"nm":"Group 1","bm":0,"hd":false}],"ip":10,"op":160,"st":10,"ct":1,"bm":0},{"ddd":0,"ind":13,"ty":4,"nm":"S 1","sr":1,"ks":{"o":{"a":1,"k":[{"i":{"x":[0.667],"y":[1]},"o":{"x":[0.333],"y":[0]},"t":26.667,"s":[100]},{"t":40,"s":[0]}]},"r":{"a":1,"k":[{"i":{"x":[0.667],"y":[1]},"o":{"x":[0.333],"y":[0]},"t":0,"s":[60]},{"t":40,"s":[0]}]},"p":{"a":0,"k":[1157.757,793.818,0]},"a":{"a":0,"k":[504.489,-82.705,0]},"s":{"a":1,"k":[{"i":{"x":[0.667,0.667,0.667],"y":[1,1,1]},"o":{"x":[0.333,0.333,0.333],"y":[0,0,0]},"t":0,"s":[0,0,100]},{"t":40,"s":[80,80,100]}]}},"ao":0,"shapes":[{"ty":"gr","it":[{"ind":0,"ty":"sh","ks":{"a":0,"k":{"i":[[2.578,3.745],[0,0],[-1.54,2.217],[0,0],[-2.58,-3.714],[0,0],[1.53,-2.223],[0,0]],"o":[[0,0],[-1.53,-2.223],[0,0],[2.58,-3.714],[0,0],[1.54,2.217],[0,0],[-2.578,3.745]],"v":[[499.147,-51.905],[480.391,-79.152],[480.407,-86.53],[499.162,-113.529],[509.816,-113.529],[528.572,-86.53],[528.588,-79.152],[509.832,-51.905]],"c":true}},"nm":"Path 1","hd":false},{"ty":"fl","c":{"a":0,"k":[0.984313726425,0.878431379795,0.831372559071,1]},"o":{"a":0,"k":100},"r":1,"bm":0,"nm":"Fill 1","hd":false},{"ty":"tr","p":{"a":0,"k":[0,0]},"a":{"a":0,"k":[0,0]},"s":{"a":0,"k":[100,100]},"r":{"a":0,"k":0},"o":{"a":0,"k":100},"sk":{"a":0,"k":0},"sa":{"a":0,"k":0},"nm":"Transform"}],"nm":"Group 1","bm":0,"hd":false}],"ip":0,"op":150,"st":0,"ct":1,"bm":0},{"ddd":0,"ind":14,"ty":4,"nm":"Star 3","sr":1,"ks":{"o":{"a":0,"k":100},"r":{"a":1,"k":[{"i":{"x":[0.667],"y":[0.706]},"o":{"x":[0.333],"y":[0]},"t":42.247,"s":[-10]},{"t":80,"s":[10]}]},"p":{"k":[{"s":[754.831,296.917,0],"t":44.134765625,"i":{"x":1,"y":1},"o":{"x":0,"y":0}},{"s":[755.409,297.009,0],"t":47.134765625,"i":{"x":1,"y":1},"o":{"x":0,"y":0}},{"s":[756.042,297.065,0],"t":50.134765625,"i":{"x":1,"y":1},"o":{"x":0,"y":0}},{"s":[756.718,297.103,0],"t":53.134765625,"i":{"x":1,"y":1},"o":{"x":0,"y":0}},{"s":[757.421,297.147,0],"t":56.134765625,"i":{"x":1,"y":1},"o":{"x":0,"y":0}},{"s":[758.133,297.212,0],"t":59.134765625,"i":{"x":1,"y":1},"o":{"x":0,"y":0}},{"s":[758.831,297.273,0],"t":62.134765625,"i":{"x":1,"y":1},"o":{"x":0,"y":0}},{"s":[759.493,297.334,0],"t":65.134765625,"i":{"x":1,"y":1},"o":{"x":0,"y":0}},{"s":[760.097,297.4,0],"t":68.134765625,"i":{"x":1,"y":1},"o":{"x":0,"y":0}},{"s":[760.772,297.49,0],"t":72.134765625,"i":{"x":1,"y":1},"o":{"x":0,"y":0}}]},"a":{"a":0,"k":[0,0,0]},"s":{"a":1,"k":[{"i":{"x":[0.667,0.667,0.667],"y":[1,1,1]},"o":{"x":[0.333,0.333,0.333],"y":[0,0,0]},"t":42.247,"s":[0,0,100]},{"i":{"x":[0.667,0.667,0.667],"y":[1,1,1]},"o":{"x":[0.333,0.333,0.333],"y":[0,0,0]},"t":58.429,"s":[69.6,69.6,100]},{"t":80,"s":[0,0,100]}]}},"ao":0,"shapes":[{"ty":"gr","it":[{"ind":0,"ty":"sh","ks":{"a":1,"k":[{"i":{"x":0.667,"y":1},"o":{"x":0.333,"y":0},"t":44.657,"s":[{"i":[[-3.344,-5.585],[-6.333,-2.991],[-6.685,2.287],[-6.861,0.352],[-1.407,4.222],[2.639,4.398],[3.167,-0.352],[8.796,0.528],[6.157,-3.343],[-2.287,-6.177]],"o":[[2.563,4.282],[6.333,2.991],[6.685,-2.287],[6.861,-0.352],[1.407,-4.222],[-2.639,-4.398],[-3.167,0.352],[-8.796,-0.528],[-6.157,3.343],[2.287,6.177]],"v":[[-12.446,6.48],[-16.744,33.104],[2.96,13.752],[24.071,28.53],[19.145,-2.081],[39.201,-16.155],[10.023,-16.567],[-3.021,-33.396],[-13.225,-12.021],[-39.262,-0.694]],"c":true}]},{"i":{"x":0.667,"y":1},"o":{"x":0.333,"y":0},"t":60.722,"s":[{"i":[[-3.344,-5.585],[-6.333,-2.991],[-6.685,2.287],[-6.861,0.352],[-1.407,4.222],[2.639,4.398],[3.167,-0.352],[8.796,0.528],[6.157,-3.343],[-2.287,-6.177]],"o":[[2.563,4.282],[6.333,2.991],[6.685,-2.287],[6.861,-0.352],[1.407,-4.222],[-2.639,-4.398],[-3.167,0.352],[-8.796,-0.528],[-6.157,3.343],[2.287,6.177]],"v":[[-12.446,6.48],[-17.994,37.604],[2.96,13.752],[26.321,32.53],[19.145,-2.081],[45.201,-16.227],[10.023,-16.567],[-4.771,-38.646],[-13.225,-12.021],[-46.262,1.806]],"c":true}]},{"t":76.7880859375,"s":[{"i":[[-3.344,-5.585],[-6.333,-2.991],[-6.685,2.287],[-6.861,0.352],[-1.407,4.222],[2.639,4.398],[3.167,-0.352],[8.796,0.528],[6.157,-3.343],[-2.287,-6.177]],"o":[[2.563,4.282],[6.333,2.991],[6.685,-2.287],[6.861,-0.352],[1.407,-4.222],[-2.639,-4.398],[-3.167,0.352],[-8.796,-0.528],[-6.157,3.343],[2.287,6.177]],"v":[[-12.446,6.48],[-16.744,33.104],[2.96,13.752],[24.071,28.53],[19.145,-2.081],[39.201,-16.155],[10.023,-16.567],[-3.021,-33.396],[-13.225,-12.021],[-39.262,-0.694]],"c":true}]}]},"nm":"Path 1","hd":false},{"ty":"fl","c":{"a":0,"k":[0.043,0.451,0.682]},"o":{"a":0,"k":100},"r":1,"bm":0,"nm":"Fill 1","hd":false},{"ty":"tr","p":{"a":0,"k":[0,0]},"a":{"a":0,"k":[0,0]},"s":{"a":0,"k":[100,100]},"r":{"a":0,"k":0},"o":{"a":0,"k":100},"sk":{"a":0,"k":0},"sa":{"a":0,"k":0},"nm":"Transform"}],"nm":"Group 1","bm":0,"hd":false}],"ip":40.134765625,"op":80,"st":47,"ct":1,"bm":0},{"ddd":0,"ind":15,"ty":4,"nm":"Star 2","sr":1,"ks":{"o":{"a":0,"k":100},"r":{"a":1,"k":[{"i":{"x":[0.667],"y":[1.294]},"o":{"x":[0.333],"y":[0]},"t":0,"s":[10]},{"t":42.2470703125,"s":[-10]}]},"p":{"k":[{"s":[752.545,295.114,0],"t":1,"i":{"x":1,"y":1},"o":{"x":0,"y":0}},{"s":[752.523,295.338,0],"t":2,"i":{"x":1,"y":1},"o":{"x":0,"y":0}},{"s":[752.508,295.547,0],"t":3,"i":{"x":1,"y":1},"o":{"x":0,"y":0}},{"s":[752.499,295.742,0],"t":4,"i":{"x":1,"y":1},"o":{"x":0,"y":0}},{"s":[752.496,295.92,0],"t":5,"i":{"x":1,"y":1},"o":{"x":0,"y":0}},{"s":[752.5,296.083,0],"t":6,"i":{"x":1,"y":1},"o":{"x":0,"y":0}},{"s":[752.527,296.359,0],"t":8,"i":{"x":1,"y":1},"o":{"x":0,"y":0}},{"s":[752.617,296.65,0],"t":11,"i":{"x":1,"y":1},"o":{"x":0,"y":0}},{"s":[753.32,296.614,0],"t":21,"i":{"x":1,"y":1},"o":{"x":0,"y":0}},{"s":[753.637,296.366,0],"t":24,"i":{"x":1,"y":1},"o":{"x":0,"y":0}},{"s":[753.869,296.166,0],"t":26,"i":{"x":1,"y":1},"o":{"x":0,"y":0}},{"s":[754.12,295.952,0],"t":28,"i":{"x":1,"y":1},"o":{"x":0,"y":0}},{"s":[754.401,295.74,0],"t":30,"i":{"x":1,"y":1},"o":{"x":0,"y":0}},{"s":[754.713,295.535,0],"t":32,"i":{"x":1,"y":1},"o":{"x":0,"y":0}},{"s":[755.229,295.25,0],"t":35,"i":{"x":1,"y":1},"o":{"x":0,"y":0}},{"s":[755.789,295,0],"t":38,"i":{"x":1,"y":1},"o":{"x":0,"y":0}}]},"a":{"a":0,"k":[0,0,0]},"s":{"a":1,"k":[{"i":{"x":[0.667,0.667,0.667],"y":[1,1,1]},"o":{"x":[0.333,0.333,0.333],"y":[0,0,0]},"t":0,"s":[0,0,100]},{"i":{"x":[0.667,0.667,0.667],"y":[1,1,1]},"o":{"x":[0.333,0.333,0.333],"y":[0,0,0]},"t":17.978,"s":[97.6,97.6,100]},{"t":42.2470703125,"s":[0,0,100]}]}},"ao":0,"shapes":[{"ty":"gr","it":[{"ind":0,"ty":"sh","ks":{"a":1,"k":[{"i":{"x":0.667,"y":1},"o":{"x":0.333,"y":0},"t":2.697,"s":[{"i":[[-3.344,-5.585],[-6.333,-2.991],[-6.685,2.287],[-6.861,0.352],[-1.407,4.222],[2.639,4.398],[3.167,-0.352],[8.796,0.528],[6.157,-3.343],[-2.287,-6.177]],"o":[[2.563,4.282],[6.333,2.991],[6.685,-2.287],[6.861,-0.352],[1.407,-4.222],[-2.639,-4.398],[-3.167,0.352],[-8.796,-0.528],[-6.157,3.343],[2.287,6.177]],"v":[[-12.446,6.48],[-16.744,33.104],[2.96,13.752],[24.071,28.53],[19.145,-2.081],[39.201,-16.155],[10.023,-16.567],[-3.021,-33.396],[-13.225,-12.021],[-39.262,-0.694]],"c":true}]},{"i":{"x":0.667,"y":1},"o":{"x":0.333,"y":0},"t":20.675,"s":[{"i":[[-3.344,-5.585],[-6.333,-2.991],[-6.685,2.287],[-6.861,0.352],[-1.407,4.222],[2.639,4.398],[3.167,-0.352],[8.796,0.528],[6.157,-3.343],[-2.287,-6.177]],"o":[[2.563,4.282],[6.333,2.991],[6.685,-2.287],[6.861,-0.352],[1.407,-4.222],[-2.639,-4.398],[-3.167,0.352],[-8.796,-0.528],[-6.157,3.343],[2.287,6.177]],"v":[[-12.446,6.48],[-17.994,37.604],[2.96,13.752],[26.321,32.53],[19.145,-2.081],[45.201,-16.227],[10.023,-16.567],[-4.771,-38.646],[-13.225,-12.021],[-46.262,1.806]],"c":true}]},{"t":38.6513671875,"s":[{"i":[[-3.344,-5.585],[-6.333,-2.991],[-6.685,2.287],[-6.861,0.352],[-1.407,4.222],[2.639,4.398],[3.167,-0.352],[8.796,0.528],[6.157,-3.343],[-2.287,-6.177]],"o":[[2.563,4.282],[6.333,2.991],[6.685,-2.287],[6.861,-0.352],[1.407,-4.222],[-2.639,-4.398],[-3.167,0.352],[-8.796,-0.528],[-6.157,3.343],[2.287,6.177]],"v":[[-12.446,6.48],[-16.744,33.104],[2.96,13.752],[24.071,28.53],[19.145,-2.081],[39.201,-16.155],[10.023,-16.567],[-3.021,-33.396],[-13.225,-12.021],[-39.262,-0.694]],"c":true}]}]},"nm":"Path 1","hd":false},{"ty":"fl","c":{"a":0,"k":[0.043,0.451,0.682]},"o":{"a":0,"k":100},"r":1,"bm":0,"nm":"Fill 1","hd":false},{"ty":"tr","p":{"a":0,"k":[0,0]},"a":{"a":0,"k":[0,0]},"s":{"a":0,"k":[100,100]},"r":{"a":0,"k":0},"o":{"a":0,"k":100},"sk":{"a":0,"k":0},"sa":{"a":0,"k":0},"nm":"Transform"}],"nm":"Group 1","bm":0,"hd":false}],"ip":0,"op":40.134765625,"st":0,"ct":1,"bm":0},{"ddd":0,"ind":16,"ty":4,"nm":"Line ch","sr":1,"ks":{"o":{"a":1,"k":[{"i":{"x":[0.833],"y":[0.833]},"o":{"x":[0.167],"y":[0.167]},"t":45,"s":[100]},{"t":50,"s":[0]}]},"r":{"a":0,"k":87},"p":{"a":0,"k":[793.116,387.822,0]},"a":{"a":0,"k":[0,0,0]},"s":{"a":0,"k":[96,96,100]}},"ao":0,"shapes":[{"ty":"gr","it":[{"ind":0,"ty":"sh","ks":{"a":0,"k":{"i":[[0,0],[-50.296,31.45],[19.513,-13.369],[-65.032,47.115],[0,0]],"o":[[0,0],[50.296,-31.45],[-19.513,13.369],[65.032,-47.115],[0,0]],"v":[[205.945,443.099],[300.588,488.844],[287.16,429.75],[411.336,440.679],[449.112,336.662]],"c":false}},"nm":"Path 1","hd":false},{"ty":"st","c":{"a":0,"k":[0.043,0.451,0.682]},"o":{"a":0,"k":100},"w":{"a":0,"k":2},"lc":2,"lj":2,"bm":0,"nm":"Stroke 1","hd":false},{"ty":"tr","p":{"a":0,"k":[0,0]},"a":{"a":0,"k":[0,0]},"s":{"a":0,"k":[100,100]},"r":{"a":0,"k":0},"o":{"a":0,"k":100},"sk":{"a":0,"k":0},"sa":{"a":0,"k":0},"nm":"Transform"}],"nm":"Group 1","bm":0,"hd":false},{"ty":"tm","s":{"a":1,"k":[{"i":{"x":[0.833],"y":[0.833]},"o":{"x":[0.333],"y":[0]},"t":37,"s":[0]},{"t":50,"s":[100]}]},"e":{"a":1,"k":[{"i":{"x":[0.25],"y":[1]},"o":{"x":[0.167],"y":[0.167]},"t":20,"s":[0]},{"t":50,"s":[100]}]},"o":{"a":0,"k":0},"m":1,"nm":"Trim In Path","hd":false}],"ip":20,"op":170,"st":20,"ct":1,"bm":0},{"ddd":0,"ind":17,"ty":4,"nm":"ch","sr":1,"ks":{"o":{"a":1,"k":[{"i":{"x":[0.833],"y":[0.833]},"o":{"x":[0.167],"y":[0.167]},"t":45,"s":[100]},{"t":50,"s":[0]}]},"r":{"a":1,"k":[{"i":{"x":[0.833],"y":[0.833]},"o":{"x":[0.167],"y":[0.167]},"t":20,"s":[251]},{"i":{"x":[0.833],"y":[0.833]},"o":{"x":[0.167],"y":[0.167]},"t":21.5,"s":[251]},{"i":{"x":[0.833],"y":[0.833]},"o":{"x":[0.167],"y":[0.167]},"t":23,"s":[209]},{"i":{"x":[0.833],"y":[0.833]},"o":{"x":[0.167],"y":[0.167]},"t":25,"s":[149]},{"i":{"x":[0.833],"y":[0.833]},"o":{"x":[0.167],"y":[0.167]},"t":26,"s":[43]},{"i":{"x":[0.833],"y":[0.833]},"o":{"x":[0.167],"y":[0.167]},"t":27,"s":[-110.333]},{"i":{"x":[0.833],"y":[0.833]},"o":{"x":[0.167],"y":[0.167]},"t":28,"s":[-148]},{"i":{"x":[0.833],"y":[0.833]},"o":{"x":[0.167],"y":[0.167]},"t":29,"s":[-157]},{"i":{"x":[0.833],"y":[0.833]},"o":{"x":[0.167],"y":[0.167]},"t":30.5,"s":[-177]},{"i":{"x":[0.833],"y":[0.833]},"o":{"x":[0.167],"y":[0.167]},"t":32,"s":[-197]},{"i":{"x":[0.833],"y":[0.833]},"o":{"x":[0.167],"y":[0.167]},"t":35,"s":[-216]},{"i":{"x":[0.833],"y":[0.833]},"o":{"x":[0.167],"y":[0.167]},"t":36.5,"s":[-224]},{"i":{"x":[0.833],"y":[0.833]},"o":{"x":[0.167],"y":[0.167]},"t":38,"s":[-235]},{"i":{"x":[0.833],"y":[0.833]},"o":{"x":[0.167],"y":[0.167]},"t":39.5,"s":[-246]},{"i":{"x":[0.833],"y":[0.833]},"o":{"x":[0.167],"y":[0.167]},"t":41,"s":[-256]},{"i":{"x":[0.833],"y":[0.833]},"o":{"x":[0.167],"y":[0.167]},"t":42.5,"s":[-263]},{"i":{"x":[0.833],"y":[0.833]},"o":{"x":[0.167],"y":[0.167]},"t":44,"s":[-267]},{"t":50,"s":[-273]}]},"p":{"a":1,"k":[{"i":{"x":0.64,"y":0.552},"o":{"x":0.167,"y":0.167},"t":20,"s":[378.672,607.521,0],"to":[0,0,0],"ti":[-32.677,-46.638,0]},{"i":{"x":0.619,"y":0.653},"o":{"x":0.295,"y":0.311},"t":23.867,"s":[339.571,700.552,0],"to":[32.677,46.638,0],"ti":[13.798,18.035,0]},{"i":{"x":0.577,"y":0.698},"o":{"x":0.259,"y":0.345},"t":26.523,"s":[395.549,684.71,0],"to":[-13.798,-18.035,0],"ti":[-48.436,-59.978,0]},{"i":{"x":0.541,"y":1},"o":{"x":0.227,"y":0.576},"t":32.543,"s":[391.31,804.304,0],"to":[48.436,59.978,0],"ti":[0,0,0]},{"t":50,"s":[492.928,835.294,0]}]},"a":{"a":0,"k":[450.607,336.662,0]},"s":{"a":0,"k":[96,96,100]}},"ao":0,"shapes":[{"ty":"gr","it":[{"ind":0,"ty":"sh","ks":{"a":0,"k":{"i":[[0,0],[-2.614,9.408],[0,0],[-7.661,-4.327],[0,0]],"o":[[0,0],[1.987,-7.151],[0,0],[6.102,3.446],[0,0]],"v":[[441.107,366.969],[448.106,355.329],[449.112,336.662],[462.036,347.97],[474.133,351.897]],"c":false}},"nm":"Path 1","hd":false},{"ty":"st","c":{"a":0,"k":[0.043,0.451,0.682]},"o":{"a":0,"k":100},"w":{"a":0,"k":2},"lc":2,"lj":2,"bm":0,"nm":"Stroke 1","hd":false},{"ty":"tr","p":{"a":0,"k":[0,0]},"a":{"a":0,"k":[0,0]},"s":{"a":0,"k":[100,100]},"r":{"a":0,"k":0},"o":{"a":0,"k":100},"sk":{"a":0,"k":0},"sa":{"a":0,"k":0},"nm":"Transform"}],"nm":"Group 1","bm":0,"hd":false}],"ip":20,"op":170,"st":20,"ct":1,"bm":0},{"ddd":0,"ind":18,"ty":4,"nm":"Isolation Mode","sr":1,"ks":{"o":{"a":0,"k":100},"r":{"a":0,"k":0},"p":{"a":0,"k":[826.947,1296.802,0]},"a":{"a":0,"k":[26.947,496.802,0]},"s":{"a":0,"k":[100,100,100]}},"ao":0,"shapes":[{"ty":"gr","it":[{"ind":0,"ty":"sh","ks":{"a":0,"k":{"i":[[13.579,0],[0,0],[0,-13.579],[0,0],[0,0],[0,0]],"o":[[0,0],[-13.579,0],[0,0],[0,0],[0,0],[0,-13.579]],"v":[[39.114,488.125],[14.78,488.125],[-9.806,512.711],[-9.806,512.711],[63.701,512.711],[63.701,512.711]],"c":true}},"nm":"Path 1","hd":false},{"ty":"fl","c":{"a":0,"k":[0.106,0.925,0.114]},"o":{"a":0,"k":100},"r":1,"bm":0,"nm":"Fill 1","hd":false},{"ty":"tr","p":{"a":0,"k":[0,0]},"a":{"a":0,"k":[0,0]},"s":{"a":0,"k":[100,100]},"r":{"a":0,"k":0},"o":{"a":0,"k":100},"sk":{"a":0,"k":0},"sa":{"a":0,"k":0},"nm":"Transform"}],"nm":"Group 1","bm":0,"hd":false},{"ty":"gr","it":[{"ind":0,"ty":"sh","ks":{"a":0,"k":{"i":[[6.39,0],[0,0],[0,6.39],[0,0],[-6.39,0],[0,0],[0,-6.39],[0,0]],"o":[[0,0],[-6.39,0],[0,0],[0,-6.39],[0,0],[6.39,0],[0,0],[0,6.39]],"v":[[355.829,535.851],[-301.935,535.851],[-313.505,524.281],[-313.505,524.281],[-301.935,512.711],[355.829,512.711],[367.399,524.281],[367.399,524.281]],"c":true}},"nm":"Path 1","hd":false},{"ty":"fl","c":{"a":0,"k":[0.106,0.925,0.114]},"o":{"a":0,"k":100},"r":1,"bm":0,"nm":"Fill 1","hd":false},{"ty":"tr","p":{"a":0,"k":[0,0]},"a":{"a":0,"k":[0,0]},"s":{"a":0,"k":[100,100]},"r":{"a":0,"k":0},"o":{"a":0,"k":100},"sk":{"a":0,"k":0},"sa":{"a":0,"k":0},"nm":"Transform"}],"nm":"Group 2","bm":0,"hd":false},{"ty":"gr","it":[{"ty":"gr","it":[{"ind":0,"ty":"sh","ks":{"a":0,"k":{"i":[[0,0],[0,0]],"o":[[0,0],[0,0]],"v":[[26.947,483.029],[26.947,507.477]],"c":false}},"nm":"Path 1","hd":false},{"ty":"st","c":{"a":0,"k":[1,1,1,1]},"o":{"a":0,"k":100},"w":{"a":0,"k":2},"lc":2,"lj":2,"bm":0,"nm":"Stroke 1","hd":false},{"ty":"tr","p":{"a":0,"k":[0,0]},"a":{"a":0,"k":[0,0]},"s":{"a":0,"k":[100,100]},"r":{"a":0,"k":0},"o":{"a":0,"k":100},"sk":{"a":0,"k":0},"sa":{"a":0,"k":0},"nm":"Transform"}],"nm":"Group 1","bm":0,"hd":false},{"ty":"gr","it":[{"ind":0,"ty":"sh","ks":{"a":0,"k":{"i":[[0,0],[-43.968,0.733],[-41.176,-7.27]],"o":[[45.585,-7.219],[41.341,-0.689],[0,0]],"v":[[-299.649,510.367],[-116.177,495.015],[-1.597,502.822]],"c":false}},"nm":"Path 1","hd":false},{"ty":"st","c":{"a":0,"k":[1,1,1,1]},"o":{"a":0,"k":100},"w":{"a":0,"k":2},"lc":2,"lj":2,"bm":0,"nm":"Stroke 1","hd":false},{"ty":"tr","p":{"a":0,"k":[0,0]},"a":{"a":0,"k":[0,0]},"s":{"a":0,"k":[100,100]},"r":{"a":0,"k":0},"o":{"a":0,"k":100},"sk":{"a":0,"k":0},"sa":{"a":0,"k":0},"nm":"Transform"}],"nm":"Group 2","bm":0,"hd":false},{"ty":"gr","it":[{"ind":0,"ty":"sh","ks":{"a":0,"k":{"i":[[0,0],[-49.189,5.092],[-39.33,-20.022]],"o":[[30.878,-9.378],[59.208,-6.129],[0,0]],"v":[[-300.496,502.822],[-152.676,475.596],[21.072,497.074]],"c":false}},"nm":"Path 1","hd":false},{"ty":"st","c":{"a":0,"k":[1,1,1,1]},"o":{"a":0,"k":100},"w":{"a":0,"k":2},"lc":2,"lj":2,"bm":0,"nm":"Stroke 1","hd":false},{"ty":"tr","p":{"a":0,"k":[0,0]},"a":{"a":0,"k":[0,0]},"s":{"a":0,"k":[100,100]},"r":{"a":0,"k":0},"o":{"a":0,"k":100},"sk":{"a":0,"k":0},"sa":{"a":0,"k":0},"nm":"Transform"}],"nm":"Group 3","bm":0,"hd":false},{"ty":"gr","it":[{"ind":0,"ty":"sh","ks":{"a":0,"k":{"i":[[58.113,-7.436],[18.08,-12.174],[-0.594,-4.519],[-1.213,-4.133],[-4.887,2.956],[1.536,15.328]],"o":[[-58.025,7.424],[-2.663,1.793],[0.121,0.921],[0.357,1.216],[3.588,-2.17],[-1.872,-18.686]],"v":[[-124.617,459.236],[-297.179,496.643],[-300.375,504.062],[-298.03,515.079],[28.42,512.203],[30.233,492.47]],"c":true}},"nm":"Path 1","hd":false},{"ty":"fl","c":{"a":0,"k":[0.984313726425,0.878431379795,0.831372559071,1]},"o":{"a":0,"k":100},"r":1,"bm":0,"nm":"Fill 1","hd":false},{"ty":"tr","p":{"a":0,"k":[0,0]},"a":{"a":0,"k":[0,0]},"s":{"a":0,"k":[100,100]},"r":{"a":0,"k":0},"o":{"a":0,"k":100},"sk":{"a":0,"k":0},"sa":{"a":0,"k":0},"nm":"Transform"}],"nm":"Group 4","bm":0,"hd":false},{"ty":"tr","p":{"a":0,"k":[0,0]},"a":{"a":0,"k":[0,0]},"s":{"a":0,"k":[100,100]},"r":{"a":0,"k":0},"o":{"a":0,"k":100},"sk":{"a":0,"k":0},"sa":{"a":0,"k":0},"nm":"Transform"}],"nm":"Group 3","bm":0,"hd":false},{"ty":"gr","it":[{"ty":"gr","it":[{"ind":0,"ty":"sh","ks":{"a":0,"k":{"i":[[0,0],[43.968,0.733],[41.176,-7.27]],"o":[[-45.585,-7.219],[-41.341,-0.689],[0,0]],"v":[[352.566,511.967],[178.271,497.041],[54.515,504.421]],"c":false}},"nm":"Path 1","hd":false},{"ty":"st","c":{"a":0,"k":[1,1,1,1]},"o":{"a":0,"k":100},"w":{"a":0,"k":2},"lc":2,"lj":2,"bm":0,"nm":"Stroke 1","hd":false},{"ty":"tr","p":{"a":0,"k":[0,0]},"a":{"a":0,"k":[0,0]},"s":{"a":0,"k":[100,100]},"r":{"a":0,"k":0},"o":{"a":0,"k":100},"sk":{"a":0,"k":0},"sa":{"a":0,"k":0},"nm":"Transform"}],"nm":"Group 1","bm":0,"hd":false},{"ty":"gr","it":[{"ind":0,"ty":"sh","ks":{"a":0,"k":{"i":[[0,0],[46.026,3.493],[39.33,-20.022]],"o":[[-30.878,-9.378],[-59.741,-4.534],[0,0]],"v":[[353.414,504.421],[205.594,477.195],[31.846,498.673]],"c":false}},"nm":"Path 1","hd":false},{"ty":"st","c":{"a":0,"k":[1,1,1,1]},"o":{"a":0,"k":100},"w":{"a":0,"k":2},"lc":2,"lj":2,"bm":0,"nm":"Stroke 1","hd":false},{"ty":"tr","p":{"a":0,"k":[0,0]},"a":{"a":0,"k":[0,0]},"s":{"a":0,"k":[100,100]},"r":{"a":0,"k":0},"o":{"a":0,"k":100},"sk":{"a":0,"k":0},"sa":{"a":0,"k":0},"nm":"Transform"}],"nm":"Group 2","bm":0,"hd":false},{"ty":"gr","it":[{"ind":0,"ty":"sh","ks":{"a":0,"k":{"i":[[-45.889,-5.127],[-18.08,-12.174],[0.594,-4.519],[1.213,-4.133],[4.887,2.956],[-1.536,15.328]],"o":[[58.425,6.527],[2.663,1.793],[-0.121,0.921],[-0.357,1.216],[-3.588,-2.17],[1.872,-18.686]],"v":[[170.791,459.392],[350.097,498.242],[353.292,505.661],[350.947,516.679],[24.497,513.802],[22.684,494.069]],"c":true}},"nm":"Path 1","hd":false},{"ty":"fl","c":{"a":0,"k":[0.984313726425,0.878431379795,0.831372559071,1]},"o":{"a":0,"k":100},"r":1,"bm":0,"nm":"Fill 1","hd":false},{"ty":"tr","p":{"a":0,"k":[0,0]},"a":{"a":0,"k":[0,0]},"s":{"a":0,"k":[100,100]},"r":{"a":0,"k":0},"o":{"a":0,"k":100},"sk":{"a":0,"k":0},"sa":{"a":0,"k":0},"nm":"Transform"}],"nm":"Group 3","bm":0,"hd":false},{"ty":"tr","p":{"a":0,"k":[0,0]},"a":{"a":0,"k":[0,0]},"s":{"a":0,"k":[100,100]},"r":{"a":0,"k":0},"o":{"a":0,"k":100},"sk":{"a":0,"k":0},"sa":{"a":0,"k":0},"nm":"Transform"}],"nm":"Group 4","bm":0,"hd":false}],"ip":0,"op":150,"st":0,"ct":1,"bm":0},{"ddd":0,"ind":19,"ty":4,"nm":"Layer 2","sr":1,"ks":{"o":{"a":0,"k":100},"r":{"k":[{"s":[-3.376],"t":0,"i":{"x":[1],"y":[1]},"o":{"x":[0],"y":[0]}},{"s":[-3.078],"t":1,"i":{"x":[1],"y":[1]},"o":{"x":[0],"y":[0]}},{"s":[-2.755],"t":2,"i":{"x":[1],"y":[1]},"o":{"x":[0],"y":[0]}},{"s":[-2.409],"t":3,"i":{"x":[1],"y":[1]},"o":{"x":[0],"y":[0]}},{"s":[-2.042],"t":4,"i":{"x":[1],"y":[1]},"o":{"x":[0],"y":[0]}},{"s":[-1.656],"t":5,"i":{"x":[1],"y":[1]},"o":{"x":[0],"y":[0]}},{"s":[-1.253],"t":6,"i":{"x":[1],"y":[1]},"o":{"x":[0],"y":[0]}},{"s":[-0.835],"t":7,"i":{"x":[1],"y":[1]},"o":{"x":[0],"y":[0]}},{"s":[-0.403],"t":8,"i":{"x":[1],"y":[1]},"o":{"x":[0],"y":[0]}},{"s":[0.041],"t":9,"i":{"x":[1],"y":[1]},"o":{"x":[0],"y":[0]}},{"s":[0.494],"t":10,"i":{"x":[1],"y":[1]},"o":{"x":[0],"y":[0]}},{"s":[0.955],"t":11,"i":{"x":[1],"y":[1]},"o":{"x":[0],"y":[0]}},{"s":[1.422],"t":12,"i":{"x":[1],"y":[1]},"o":{"x":[0],"y":[0]}},{"s":[1.894],"t":13,"i":{"x":[1],"y":[1]},"o":{"x":[0],"y":[0]}},{"s":[2.367],"t":14,"i":{"x":[1],"y":[1]},"o":{"x":[0],"y":[0]}},{"s":[2.842],"t":15,"i":{"x":[1],"y":[1]},"o":{"x":[0],"y":[0]}},{"s":[3.316],"t":16,"i":{"x":[1],"y":[1]},"o":{"x":[0],"y":[0]}},{"s":[3.788],"t":17,"i":{"x":[1],"y":[1]},"o":{"x":[0],"y":[0]}},{"s":[4.255],"t":18,"i":{"x":[1],"y":[1]},"o":{"x":[0],"y":[0]}},{"s":[4.718],"t":19,"i":{"x":[1],"y":[1]},"o":{"x":[0],"y":[0]}},{"s":[5.175],"t":20,"i":{"x":[1],"y":[1]},"o":{"x":[0],"y":[0]}},{"s":[5.624],"t":21,"i":{"x":[1],"y":[1]},"o":{"x":[0],"y":[0]}},{"s":[6.064],"t":22,"i":{"x":[1],"y":[1]},"o":{"x":[0],"y":[0]}},{"s":[6.496],"t":23,"i":{"x":[1],"y":[1]},"o":{"x":[0],"y":[0]}},{"s":[6.917],"t":24,"i":{"x":[1],"y":[1]},"o":{"x":[0],"y":[0]}},{"s":[7.273],"t":25,"i":{"x":[1],"y":[1]},"o":{"x":[0],"y":[0]}},{"s":[7.536],"t":26,"i":{"x":[1],"y":[1]},"o":{"x":[0],"y":[0]}},{"s":[7.713],"t":27,"i":{"x":[1],"y":[1]},"o":{"x":[0],"y":[0]}},{"s":[7.81],"t":28,"i":{"x":[1],"y":[1]},"o":{"x":[0],"y":[0]}},{"s":[7.834],"t":29,"i":{"x":[1],"y":[1]},"o":{"x":[0],"y":[0]}},{"s":[7.791],"t":30,"i":{"x":[1],"y":[1]},"o":{"x":[0],"y":[0]}},{"s":[7.69],"t":31,"i":{"x":[1],"y":[1]},"o":{"x":[0],"y":[0]}},{"s":[7.537],"t":32,"i":{"x":[1],"y":[1]},"o":{"x":[0],"y":[0]}},{"s":[7.34],"t":33,"i":{"x":[1],"y":[1]},"o":{"x":[0],"y":[0]}},{"s":[7.107],"t":34,"i":{"x":[1],"y":[1]},"o":{"x":[0],"y":[0]}},{"s":[6.844],"t":35,"i":{"x":[1],"y":[1]},"o":{"x":[0],"y":[0]}},{"s":[6.56],"t":36,"i":{"x":[1],"y":[1]},"o":{"x":[0],"y":[0]}},{"s":[6.263],"t":37,"i":{"x":[1],"y":[1]},"o":{"x":[0],"y":[0]}},{"s":[5.961],"t":38,"i":{"x":[1],"y":[1]},"o":{"x":[0],"y":[0]}},{"s":[5.662],"t":39,"i":{"x":[1],"y":[1]},"o":{"x":[0],"y":[0]}},{"s":[5.375],"t":40,"i":{"x":[1],"y":[1]},"o":{"x":[0],"y":[0]}},{"s":[5.107],"t":41,"i":{"x":[1],"y":[1]},"o":{"x":[0],"y":[0]}},{"s":[4.868],"t":42,"i":{"x":[1],"y":[1]},"o":{"x":[0],"y":[0]}},{"s":[4.665],"t":43,"i":{"x":[1],"y":[1]},"o":{"x":[0],"y":[0]}},{"s":[4.508],"t":44,"i":{"x":[1],"y":[1]},"o":{"x":[0],"y":[0]}},{"s":[4.347],"t":45,"i":{"x":[1],"y":[1]},"o":{"x":[0],"y":[0]}},{"s":[4.149],"t":46,"i":{"x":[1],"y":[1]},"o":{"x":[0],"y":[0]}},{"s":[3.918],"t":47,"i":{"x":[1],"y":[1]},"o":{"x":[0],"y":[0]}},{"s":[3.657],"t":48,"i":{"x":[1],"y":[1]},"o":{"x":[0],"y":[0]}},{"s":[3.369],"t":49,"i":{"x":[1],"y":[1]},"o":{"x":[0],"y":[0]}},{"s":[3.056],"t":50,"i":{"x":[1],"y":[1]},"o":{"x":[0],"y":[0]}},{"s":[2.723],"t":51,"i":{"x":[1],"y":[1]},"o":{"x":[0],"y":[0]}},{"s":[2.373],"t":52,"i":{"x":[1],"y":[1]},"o":{"x":[0],"y":[0]}},{"s":[2.009],"t":53,"i":{"x":[1],"y":[1]},"o":{"x":[0],"y":[0]}},{"s":[1.633],"t":54,"i":{"x":[1],"y":[1]},"o":{"x":[0],"y":[0]}},{"s":[1.25],"t":55,"i":{"x":[1],"y":[1]},"o":{"x":[0],"y":[0]}},{"s":[0.862],"t":56,"i":{"x":[1],"y":[1]},"o":{"x":[0],"y":[0]}},{"s":[0.473],"t":57,"i":{"x":[1],"y":[1]},"o":{"x":[0],"y":[0]}},{"s":[0.086],"t":58,"i":{"x":[1],"y":[1]},"o":{"x":[0],"y":[0]}},{"s":[-0.298],"t":59,"i":{"x":[1],"y":[1]},"o":{"x":[0],"y":[0]}},{"s":[-0.673],"t":60,"i":{"x":[1],"y":[1]},"o":{"x":[0],"y":[0]}},{"s":[-1.039],"t":61,"i":{"x":[1],"y":[1]},"o":{"x":[0],"y":[0]}},{"s":[-1.392],"t":62,"i":{"x":[1],"y":[1]},"o":{"x":[0],"y":[0]}},{"s":[-1.729],"t":63,"i":{"x":[1],"y":[1]},"o":{"x":[0],"y":[0]}},{"s":[-2.048],"t":64,"i":{"x":[1],"y":[1]},"o":{"x":[0],"y":[0]}},{"s":[-2.347],"t":65,"i":{"x":[1],"y":[1]},"o":{"x":[0],"y":[0]}},{"s":[-2.624],"t":66,"i":{"x":[1],"y":[1]},"o":{"x":[0],"y":[0]}},{"s":[-2.876],"t":67,"i":{"x":[1],"y":[1]},"o":{"x":[0],"y":[0]}},{"s":[-3.102],"t":68,"i":{"x":[1],"y":[1]},"o":{"x":[0],"y":[0]}},{"s":[-3.3],"t":69,"i":{"x":[1],"y":[1]},"o":{"x":[0],"y":[0]}},{"s":[-3.469],"t":70,"i":{"x":[1],"y":[1]},"o":{"x":[0],"y":[0]}},{"s":[-3.607],"t":71,"i":{"x":[1],"y":[1]},"o":{"x":[0],"y":[0]}},{"s":[-3.713],"t":72,"i":{"x":[1],"y":[1]},"o":{"x":[0],"y":[0]}},{"s":[-3.787],"t":73,"i":{"x":[1],"y":[1]},"o":{"x":[0],"y":[0]}},{"s":[-3.828],"t":74,"i":{"x":[1],"y":[1]},"o":{"x":[0],"y":[0]}},{"s":[-3.835],"t":75,"i":{"x":[1],"y":[1]},"o":{"x":[0],"y":[0]}},{"s":[-3.809],"t":76,"i":{"x":[1],"y":[1]},"o":{"x":[0],"y":[0]}},{"s":[-3.749],"t":77,"i":{"x":[1],"y":[1]},"o":{"x":[0],"y":[0]}},{"s":[-3.657],"t":78,"i":{"x":[1],"y":[1]},"o":{"x":[0],"y":[0]}},{"s":[-3.532],"t":79,"i":{"x":[1],"y":[1]},"o":{"x":[0],"y":[0]}}]},"p":{"k":[{"s":[1162.751,1189.805,0],"t":1,"i":{"x":1,"y":1},"o":{"x":0,"y":0}},{"s":[1163.332,1190.698,0],"t":2,"i":{"x":1,"y":1},"o":{"x":0,"y":0}},{"s":[1163.937,1191.522,0],"t":3,"i":{"x":1,"y":1},"o":{"x":0,"y":0}},{"s":[1164.562,1192.275,0],"t":4,"i":{"x":1,"y":1},"o":{"x":0,"y":0}},{"s":[1165.203,1192.955,0],"t":5,"i":{"x":1,"y":1},"o":{"x":0,"y":0}},{"s":[1165.857,1193.556,0],"t":6,"i":{"x":1,"y":1},"o":{"x":0,"y":0}},{"s":[1166.521,1194.078,0],"t":7,"i":{"x":1,"y":1},"o":{"x":0,"y":0}},{"s":[1167.191,1194.518,0],"t":8,"i":{"x":1,"y":1},"o":{"x":0,"y":0}},{"s":[1167.864,1194.873,0],"t":9,"i":{"x":1,"y":1},"o":{"x":0,"y":0}},{"s":[1168.537,1195.141,0],"t":10,"i":{"x":1,"y":1},"o":{"x":0,"y":0}},{"s":[1169.205,1195.321,0],"t":11,"i":{"x":1,"y":1},"o":{"x":0,"y":0}},{"s":[1169.866,1195.41,0],"t":12,"i":{"x":1,"y":1},"o":{"x":0,"y":0}},{"s":[1170.516,1195.408,0],"t":13,"i":{"x":1,"y":1},"o":{"x":0,"y":0}},{"s":[1171.152,1195.312,0],"t":14,"i":{"x":1,"y":1},"o":{"x":0,"y":0}},{"s":[1171.77,1195.123,0],"t":15,"i":{"x":1,"y":1},"o":{"x":0,"y":0}},{"s":[1172.941,1194.459,0],"t":17,"i":{"x":1,"y":1},"o":{"x":0,"y":0}},{"s":[1174.005,1193.415,0],"t":19,"i":{"x":1,"y":1},"o":{"x":0,"y":0}},{"s":[1174.49,1192.751,0],"t":20,"i":{"x":1,"y":1},"o":{"x":0,"y":0}},{"s":[1174.94,1191.993,0],"t":21,"i":{"x":1,"y":1},"o":{"x":0,"y":0}},{"s":[1175.352,1191.142,0],"t":22,"i":{"x":1,"y":1},"o":{"x":0,"y":0}},{"s":[1175.725,1190.199,0],"t":23,"i":{"x":1,"y":1},"o":{"x":0,"y":0}},{"s":[1176.057,1189.167,0],"t":24,"i":{"x":1,"y":1},"o":{"x":0,"y":0}},{"s":[1176.303,1188.154,0],"t":25,"i":{"x":1,"y":1},"o":{"x":0,"y":0}},{"s":[1176.445,1187.22,0],"t":26,"i":{"x":1,"y":1},"o":{"x":0,"y":0}},{"s":[1176.489,1186.359,0],"t":27,"i":{"x":1,"y":1},"o":{"x":0,"y":0}},{"s":[1176.444,1185.562,0],"t":28,"i":{"x":1,"y":1},"o":{"x":0,"y":0}},{"s":[1176.318,1184.823,0],"t":29,"i":{"x":1,"y":1},"o":{"x":0,"y":0}},{"s":[1176.118,1184.135,0],"t":30,"i":{"x":1,"y":1},"o":{"x":0,"y":0}},{"s":[1175.853,1183.492,0],"t":31,"i":{"x":1,"y":1},"o":{"x":0,"y":0}},{"s":[1175.155,1182.318,0],"t":33,"i":{"x":1,"y":1},"o":{"x":0,"y":0}},{"s":[1174.285,1181.26,0],"t":35,"i":{"x":1,"y":1},"o":{"x":0,"y":0}},{"s":[1173.305,1180.284,0],"t":37,"i":{"x":1,"y":1},"o":{"x":0,"y":0}},{"s":[1172.275,1179.367,0],"t":39,"i":{"x":1,"y":1},"o":{"x":0,"y":0}},{"s":[1171.255,1178.49,0],"t":41,"i":{"x":1,"y":1},"o":{"x":0,"y":0}},{"s":[1170.308,1177.645,0],"t":43,"i":{"x":1,"y":1},"o":{"x":0,"y":0}},{"s":[1169.45,1176.867,0],"t":45,"i":{"x":1,"y":1},"o":{"x":0,"y":0}},{"s":[1168.531,1176.315,0],"t":47,"i":{"x":1,"y":1},"o":{"x":0,"y":0}},{"s":[1167.553,1175.997,0],"t":49,"i":{"x":1,"y":1},"o":{"x":0,"y":0}},{"s":[1166.548,1175.896,0],"t":51,"i":{"x":1,"y":1},"o":{"x":0,"y":0}},{"s":[1165.542,1175.998,0],"t":53,"i":{"x":1,"y":1},"o":{"x":0,"y":0}},{"s":[1164.565,1176.287,0],"t":55,"i":{"x":1,"y":1},"o":{"x":0,"y":0}},{"s":[1163.639,1176.745,0],"t":57,"i":{"x":1,"y":1},"o":{"x":0,"y":0}},{"s":[1162.791,1177.356,0],"t":59,"i":{"x":1,"y":1},"o":{"x":0,"y":0}},{"s":[1161.707,1178.521,0],"t":62,"i":{"x":1,"y":1},"o":{"x":0,"y":0}},{"s":[1161.138,1179.439,0],"t":64,"i":{"x":1,"y":1},"o":{"x":0,"y":0}},{"s":[1160.709,1180.45,0],"t":66,"i":{"x":1,"y":1},"o":{"x":0,"y":0}},{"s":[1160.432,1181.538,0],"t":68,"i":{"x":1,"y":1},"o":{"x":0,"y":0}},{"s":[1160.317,1182.688,0],"t":70,"i":{"x":1,"y":1},"o":{"x":0,"y":0}},{"s":[1160.321,1183.28,0],"t":71,"i":{"x":1,"y":1},"o":{"x":0,"y":0}},{"s":[1160.368,1183.883,0],"t":72,"i":{"x":1,"y":1},"o":{"x":0,"y":0}},{"s":[1160.456,1184.493,0],"t":73,"i":{"x":1,"y":1},"o":{"x":0,"y":0}},{"s":[1160.586,1185.109,0],"t":74,"i":{"x":1,"y":1},"o":{"x":0,"y":0}},{"s":[1160.757,1185.73,0],"t":75,"i":{"x":1,"y":1},"o":{"x":0,"y":0}},{"s":[1160.968,1186.354,0],"t":76,"i":{"x":1,"y":1},"o":{"x":0,"y":0}},{"s":[1161.22,1186.979,0],"t":77,"i":{"x":1,"y":1},"o":{"x":0,"y":0}},{"s":[1161.509,1187.604,0],"t":78,"i":{"x":1,"y":1},"o":{"x":0,"y":0}}]},"a":{"a":0,"k":[367.399,391.185,0]},"s":{"a":0,"k":[100,100,100]}},"ao":0,"shapes":[{"ty":"gr","it":[{"ind":0,"ty":"sh","ks":{"a":0,"k":{"i":[[0,0],[-9.318,-4.589],[-7.084,12.231],[17.984,7.029],[9.675,-16.065],[-10.91,-3.497],[-9.655,15.355],[0,0]],"o":[[0,0],[9.318,4.589],[7.084,-12.231],[-17.984,-7.029],[-9.675,16.065],[10.91,3.497],[9.655,-15.355],[0,0]],"v":[[380.781,364.344],[354.133,413.883],[388.714,375.357],[396.831,333.402],[337.797,408.887],[338.541,448.815],[370.12,426.396],[400.446,382.498]],"c":false}},"nm":"Path 1","hd":false},{"ty":"st","c":{"a":0,"k":[0.612,0.733,0.984]},"o":{"a":0,"k":100},"w":{"a":0,"k":2},"lc":2,"lj":2,"bm":0,"nm":"Stroke 1","hd":false},{"ty":"tr","p":{"a":0,"k":[0,0]},"a":{"a":0,"k":[0,0]},"s":{"a":0,"k":[100,100]},"r":{"a":0,"k":0},"o":{"a":0,"k":100},"sk":{"a":0,"k":0},"sa":{"a":0,"k":0},"nm":"Transform"}],"nm":"Group 1","bm":0,"hd":false}],"ip":0,"op":150,"st":0,"ct":1,"bm":0},{"ddd":0,"ind":20,"ty":4,"nm":"Layer 1","sr":1,"ks":{"o":{"a":0,"k":100},"r":{"k":[{"s":[5.758],"t":0,"i":{"x":[1],"y":[1]},"o":{"x":[0],"y":[0]}},{"s":[6.265],"t":1,"i":{"x":[1],"y":[1]},"o":{"x":[0],"y":[0]}},{"s":[6.682],"t":2,"i":{"x":[1],"y":[1]},"o":{"x":[0],"y":[0]}},{"s":[7.014],"t":3,"i":{"x":[1],"y":[1]},"o":{"x":[0],"y":[0]}},{"s":[7.27],"t":4,"i":{"x":[1],"y":[1]},"o":{"x":[0],"y":[0]}},{"s":[7.455],"t":5,"i":{"x":[1],"y":[1]},"o":{"x":[0],"y":[0]}},{"s":[7.577],"t":6,"i":{"x":[1],"y":[1]},"o":{"x":[0],"y":[0]}},{"s":[7.643],"t":7,"i":{"x":[1],"y":[1]},"o":{"x":[0],"y":[0]}},{"s":[7.659],"t":8,"i":{"x":[1],"y":[1]},"o":{"x":[0],"y":[0]}},{"s":[7.633],"t":9,"i":{"x":[1],"y":[1]},"o":{"x":[0],"y":[0]}},{"s":[7.572],"t":10,"i":{"x":[1],"y":[1]},"o":{"x":[0],"y":[0]}},{"s":[7.483],"t":11,"i":{"x":[1],"y":[1]},"o":{"x":[0],"y":[0]}},{"s":[7.373],"t":12,"i":{"x":[1],"y":[1]},"o":{"x":[0],"y":[0]}},{"s":[7.25],"t":13,"i":{"x":[1],"y":[1]},"o":{"x":[0],"y":[0]}},{"s":[7.108],"t":14,"i":{"x":[1],"y":[1]},"o":{"x":[0],"y":[0]}},{"s":[6.929],"t":15,"i":{"x":[1],"y":[1]},"o":{"x":[0],"y":[0]}},{"s":[6.714],"t":16,"i":{"x":[1],"y":[1]},"o":{"x":[0],"y":[0]}},{"s":[6.463],"t":17,"i":{"x":[1],"y":[1]},"o":{"x":[0],"y":[0]}},{"s":[6.179],"t":18,"i":{"x":[1],"y":[1]},"o":{"x":[0],"y":[0]}},{"s":[5.862],"t":19,"i":{"x":[1],"y":[1]},"o":{"x":[0],"y":[0]}},{"s":[5.514],"t":20,"i":{"x":[1],"y":[1]},"o":{"x":[0],"y":[0]}},{"s":[5.137],"t":21,"i":{"x":[1],"y":[1]},"o":{"x":[0],"y":[0]}},{"s":[4.734],"t":22,"i":{"x":[1],"y":[1]},"o":{"x":[0],"y":[0]}},{"s":[4.305],"t":23,"i":{"x":[1],"y":[1]},"o":{"x":[0],"y":[0]}},{"s":[3.855],"t":24,"i":{"x":[1],"y":[1]},"o":{"x":[0],"y":[0]}},{"s":[3.384],"t":25,"i":{"x":[1],"y":[1]},"o":{"x":[0],"y":[0]}},{"s":[2.895],"t":26,"i":{"x":[1],"y":[1]},"o":{"x":[0],"y":[0]}},{"s":[2.392],"t":27,"i":{"x":[1],"y":[1]},"o":{"x":[0],"y":[0]}},{"s":[1.877],"t":28,"i":{"x":[1],"y":[1]},"o":{"x":[0],"y":[0]}},{"s":[1.351],"t":29,"i":{"x":[1],"y":[1]},"o":{"x":[0],"y":[0]}},{"s":[0.82],"t":30,"i":{"x":[1],"y":[1]},"o":{"x":[0],"y":[0]}},{"s":[0.284],"t":31,"i":{"x":[1],"y":[1]},"o":{"x":[0],"y":[0]}},{"s":[-0.252],"t":32,"i":{"x":[1],"y":[1]},"o":{"x":[0],"y":[0]}},{"s":[-0.787],"t":33,"i":{"x":[1],"y":[1]},"o":{"x":[0],"y":[0]}},{"s":[-1.316],"t":34,"i":{"x":[1],"y":[1]},"o":{"x":[0],"y":[0]}},{"s":[-1.837],"t":35,"i":{"x":[1],"y":[1]},"o":{"x":[0],"y":[0]}},{"s":[-2.347],"t":36,"i":{"x":[1],"y":[1]},"o":{"x":[0],"y":[0]}},{"s":[-2.844],"t":37,"i":{"x":[1],"y":[1]},"o":{"x":[0],"y":[0]}},{"s":[-3.324],"t":38,"i":{"x":[1],"y":[1]},"o":{"x":[0],"y":[0]}},{"s":[-3.783],"t":39,"i":{"x":[1],"y":[1]},"o":{"x":[0],"y":[0]}},{"s":[-4.221],"t":40,"i":{"x":[1],"y":[1]},"o":{"x":[0],"y":[0]}},{"s":[-4.633],"t":41,"i":{"x":[1],"y":[1]},"o":{"x":[0],"y":[0]}},{"s":[-5.018],"t":42,"i":{"x":[1],"y":[1]},"o":{"x":[0],"y":[0]}},{"s":[-5.372],"t":43,"i":{"x":[1],"y":[1]},"o":{"x":[0],"y":[0]}},{"s":[-5.693],"t":44,"i":{"x":[1],"y":[1]},"o":{"x":[0],"y":[0]}},{"s":[-5.979],"t":45,"i":{"x":[1],"y":[1]},"o":{"x":[0],"y":[0]}},{"s":[-6.227],"t":46,"i":{"x":[1],"y":[1]},"o":{"x":[0],"y":[0]}},{"s":[-6.436],"t":47,"i":{"x":[1],"y":[1]},"o":{"x":[0],"y":[0]}},{"s":[-6.603],"t":48,"i":{"x":[1],"y":[1]},"o":{"x":[0],"y":[0]}},{"s":[-6.727],"t":49,"i":{"x":[1],"y":[1]},"o":{"x":[0],"y":[0]}},{"s":[-6.806],"t":50,"i":{"x":[1],"y":[1]},"o":{"x":[0],"y":[0]}},{"s":[-6.839],"t":51,"i":{"x":[1],"y":[1]},"o":{"x":[0],"y":[0]}},{"s":[-6.824],"t":52,"i":{"x":[1],"y":[1]},"o":{"x":[0],"y":[0]}},{"s":[-6.761],"t":53,"i":{"x":[1],"y":[1]},"o":{"x":[0],"y":[0]}},{"s":[-6.659],"t":54,"i":{"x":[1],"y":[1]},"o":{"x":[0],"y":[0]}},{"s":[-6.536],"t":55,"i":{"x":[1],"y":[1]},"o":{"x":[0],"y":[0]}},{"s":[-6.393],"t":56,"i":{"x":[1],"y":[1]},"o":{"x":[0],"y":[0]}},{"s":[-6.23],"t":57,"i":{"x":[1],"y":[1]},"o":{"x":[0],"y":[0]}},{"s":[-6.044],"t":58,"i":{"x":[1],"y":[1]},"o":{"x":[0],"y":[0]}},{"s":[-5.835],"t":59,"i":{"x":[1],"y":[1]},"o":{"x":[0],"y":[0]}},{"s":[-5.601],"t":60,"i":{"x":[1],"y":[1]},"o":{"x":[0],"y":[0]}},{"s":[-5.339],"t":61,"i":{"x":[1],"y":[1]},"o":{"x":[0],"y":[0]}},{"s":[-5.048],"t":62,"i":{"x":[1],"y":[1]},"o":{"x":[0],"y":[0]}},{"s":[-4.723],"t":63,"i":{"x":[1],"y":[1]},"o":{"x":[0],"y":[0]}},{"s":[-4.364],"t":64,"i":{"x":[1],"y":[1]},"o":{"x":[0],"y":[0]}},{"s":[-3.965],"t":65,"i":{"x":[1],"y":[1]},"o":{"x":[0],"y":[0]}},{"s":[-3.523],"t":66,"i":{"x":[1],"y":[1]},"o":{"x":[0],"y":[0]}},{"s":[-3.035],"t":67,"i":{"x":[1],"y":[1]},"o":{"x":[0],"y":[0]}},{"s":[-2.497],"t":68,"i":{"x":[1],"y":[1]},"o":{"x":[0],"y":[0]}},{"s":[-1.904],"t":69,"i":{"x":[1],"y":[1]},"o":{"x":[0],"y":[0]}},{"s":[-1.254],"t":70,"i":{"x":[1],"y":[1]},"o":{"x":[0],"y":[0]}},{"s":[-0.54],"t":71,"i":{"x":[1],"y":[1]},"o":{"x":[0],"y":[0]}},{"s":[0.24],"t":72,"i":{"x":[1],"y":[1]},"o":{"x":[0],"y":[0]}},{"s":[1.091],"t":73,"i":{"x":[1],"y":[1]},"o":{"x":[0],"y":[0]}},{"s":[1.962],"t":74,"i":{"x":[1],"y":[1]},"o":{"x":[0],"y":[0]}},{"s":[2.764],"t":75,"i":{"x":[1],"y":[1]},"o":{"x":[0],"y":[0]}},{"s":[3.496],"t":76,"i":{"x":[1],"y":[1]},"o":{"x":[0],"y":[0]}},{"s":[4.16],"t":77,"i":{"x":[1],"y":[1]},"o":{"x":[0],"y":[0]}},{"s":[4.757],"t":78,"i":{"x":[1],"y":[1]},"o":{"x":[0],"y":[0]}},{"s":[5.289],"t":79,"i":{"x":[1],"y":[1]},"o":{"x":[0],"y":[0]}}]},"p":{"k":[{"s":[1087.51,438.574,0],"t":1,"i":{"x":1,"y":1},"o":{"x":0,"y":0}},{"s":[1087.925,438.283,0],"t":2,"i":{"x":1,"y":1},"o":{"x":0,"y":0}},{"s":[1088.59,437.912,0],"t":4,"i":{"x":1,"y":1},"o":{"x":0,"y":0}},{"s":[1089.631,438.004,0],"t":10,"i":{"x":1,"y":1},"o":{"x":0,"y":0}},{"s":[1089.859,438.433,0],"t":13,"i":{"x":1,"y":1},"o":{"x":0,"y":0}},{"s":[1089.945,438.809,0],"t":15,"i":{"x":1,"y":1},"o":{"x":0,"y":0}},{"s":[1089.951,439.04,0],"t":16,"i":{"x":1,"y":1},"o":{"x":0,"y":0}},{"s":[1089.932,439.298,0],"t":17,"i":{"x":1,"y":1},"o":{"x":0,"y":0}},{"s":[1089.889,439.581,0],"t":18,"i":{"x":1,"y":1},"o":{"x":0,"y":0}},{"s":[1089.823,439.89,0],"t":19,"i":{"x":1,"y":1},"o":{"x":0,"y":0}},{"s":[1089.734,440.221,0],"t":20,"i":{"x":1,"y":1},"o":{"x":0,"y":0}},{"s":[1089.624,440.575,0],"t":21,"i":{"x":1,"y":1},"o":{"x":0,"y":0}},{"s":[1089.493,440.948,0],"t":22,"i":{"x":1,"y":1},"o":{"x":0,"y":0}},{"s":[1089.343,441.339,0],"t":23,"i":{"x":1,"y":1},"o":{"x":0,"y":0}},{"s":[1089.174,441.747,0],"t":24,"i":{"x":1,"y":1},"o":{"x":0,"y":0}},{"s":[1088.988,442.169,0],"t":25,"i":{"x":1,"y":1},"o":{"x":0,"y":0}},{"s":[1088.786,442.603,0],"t":26,"i":{"x":1,"y":1},"o":{"x":0,"y":0}},{"s":[1088.57,443.048,0],"t":27,"i":{"x":1,"y":1},"o":{"x":0,"y":0}},{"s":[1088.341,443.5,0],"t":28,"i":{"x":1,"y":1},"o":{"x":0,"y":0}},{"s":[1088.101,443.959,0],"t":29,"i":{"x":1,"y":1},"o":{"x":0,"y":0}},{"s":[1087.851,444.421,0],"t":30,"i":{"x":1,"y":1},"o":{"x":0,"y":0}},{"s":[1087.593,444.885,0],"t":31,"i":{"x":1,"y":1},"o":{"x":0,"y":0}},{"s":[1087.328,445.347,0],"t":32,"i":{"x":1,"y":1},"o":{"x":0,"y":0}},{"s":[1087.059,445.806,0],"t":33,"i":{"x":1,"y":1},"o":{"x":0,"y":0}},{"s":[1086.787,446.26,0],"t":34,"i":{"x":1,"y":1},"o":{"x":0,"y":0}},{"s":[1086.513,446.706,0],"t":35,"i":{"x":1,"y":1},"o":{"x":0,"y":0}},{"s":[1086.24,447.142,0],"t":36,"i":{"x":1,"y":1},"o":{"x":0,"y":0}},{"s":[1085.969,447.564,0],"t":37,"i":{"x":1,"y":1},"o":{"x":0,"y":0}},{"s":[1085.702,447.972,0],"t":38,"i":{"x":1,"y":1},"o":{"x":0,"y":0}},{"s":[1085.44,448.363,0],"t":39,"i":{"x":1,"y":1},"o":{"x":0,"y":0}},{"s":[1085.185,448.735,0],"t":40,"i":{"x":1,"y":1},"o":{"x":0,"y":0}},{"s":[1084.939,449.084,0],"t":41,"i":{"x":1,"y":1},"o":{"x":0,"y":0}},{"s":[1084.704,449.41,0],"t":42,"i":{"x":1,"y":1},"o":{"x":0,"y":0}},{"s":[1084.481,449.71,0],"t":43,"i":{"x":1,"y":1},"o":{"x":0,"y":0}},{"s":[1084.271,449.982,0],"t":44,"i":{"x":1,"y":1},"o":{"x":0,"y":0}},{"s":[1084.076,450.224,0],"t":45,"i":{"x":1,"y":1},"o":{"x":0,"y":0}},{"s":[1083.736,450.611,0],"t":47,"i":{"x":1,"y":1},"o":{"x":0,"y":0}},{"s":[1083.301,450.266,0],"t":59,"i":{"x":1,"y":1},"o":{"x":0,"y":0}},{"s":[1083.436,449.928,0],"t":61,"i":{"x":1,"y":1},"o":{"x":0,"y":0}},{"s":[1083.526,449.714,0],"t":62,"i":{"x":1,"y":1},"o":{"x":0,"y":0}},{"s":[1083.632,449.464,0],"t":63,"i":{"x":1,"y":1},"o":{"x":0,"y":0}},{"s":[1083.756,449.173,0],"t":64,"i":{"x":1,"y":1},"o":{"x":0,"y":0}},{"s":[1083.899,448.835,0],"t":65,"i":{"x":1,"y":1},"o":{"x":0,"y":0}},{"s":[1084.063,448.446,0],"t":66,"i":{"x":1,"y":1},"o":{"x":0,"y":0}},{"s":[1084.25,448,0],"t":67,"i":{"x":1,"y":1},"o":{"x":0,"y":0}},{"s":[1084.46,447.491,0],"t":68,"i":{"x":1,"y":1},"o":{"x":0,"y":0}},{"s":[1084.696,446.915,0],"t":69,"i":{"x":1,"y":1},"o":{"x":0,"y":0}},{"s":[1084.959,446.265,0],"t":70,"i":{"x":1,"y":1},"o":{"x":0,"y":0}},{"s":[1085.25,445.536,0],"t":71,"i":{"x":1,"y":1},"o":{"x":0,"y":0}},{"s":[1085.571,444.722,0],"t":72,"i":{"x":1,"y":1},"o":{"x":0,"y":0}},{"s":[1085.923,443.818,0],"t":73,"i":{"x":1,"y":1},"o":{"x":0,"y":0}},{"s":[1086.269,442.884,0],"t":74,"i":{"x":1,"y":1},"o":{"x":0,"y":0}},{"s":[1086.548,442.028,0],"t":75,"i":{"x":1,"y":1},"o":{"x":0,"y":0}},{"s":[1086.761,441.251,0],"t":76,"i":{"x":1,"y":1},"o":{"x":0,"y":0}},{"s":[1086.913,440.555,0],"t":77,"i":{"x":1,"y":1},"o":{"x":0,"y":0}},{"s":[1087.007,439.939,0],"t":78,"i":{"x":1,"y":1},"o":{"x":0,"y":0}},{"s":[1087.045,439.402,0],"t":79,"i":{"x":1,"y":1},"o":{"x":0,"y":0}}]},"a":{"a":0,"k":[289.891,-364,0]},"s":{"a":0,"k":[100,100,100]}},"ao":0,"shapes":[{"ty":"gr","it":[{"ind":0,"ty":"sh","ks":{"a":0,"k":{"i":[[0,-26.496],[26.496,0],[0,26.496],[-26.496,0]],"o":[[0,26.496],[-26.496,0],[0,-26.496],[26.496,0]],"v":[[346.57,-359.024],[281.188,-316.025],[233.213,-364],[281.188,-411.975]],"c":true}},"nm":"Path 1","hd":false},{"ty":"st","c":{"a":0,"k":[0.984313726425,0.878431379795,0.831372559071,1]},"o":{"a":0,"k":100},"w":{"a":0,"k":2},"lc":2,"lj":2,"bm":0,"nm":"Stroke 1","hd":false},{"ty":"tr","p":{"a":0,"k":[0,0]},"a":{"a":0,"k":[0,0]},"s":{"a":0,"k":[100,100]},"r":{"a":0,"k":0},"o":{"a":0,"k":100},"sk":{"a":0,"k":0},"sa":{"a":0,"k":0},"nm":"Transform"}],"nm":"Group 1","bm":0,"hd":false}],"ip":0,"op":150,"st":0,"ct":1,"bm":0}],"markers":[],"props":{}}